test/test.v
module decoder3_8(
    input wire [2:0] in,
    output reg [7:0] out
);
    // always/initial 模块中只能用 reg型变量
    always @(*) begin
        case(in)
            3'h0: out = 8'h01;
            3'h1: out = 8'h02;
            3'h2: out = 8'h04;
            3'h3: out = 8'h08;
            3'h4: out = 8'h10;
            3'h5: out = 8'h20;
            3'h6: out = 8'h40;
            3'h7: out = 8'h80;
            // 避免lanth
            default: out = 8'h00;
        endcase
    end
endmodule

test/test_tb.v
`timescale 1ns/1ns        // 时间单位及=精度设置
`include "test.v"
module tb_decoder3_8();    
 
    reg [2:0] in;
 
    wire [7:0] out;
    // 初始化
    initial begin
        in <= 3'h0;
    end
    // 实现输入信号电平自动变化
    always #10 in <= {$random} % 8;
    initial begin
        $timeformat(-9, 0, "ns", 6);
        $monitor("time:%t in:%b out:%b",$time,in,out);
    end
    // 通过实例化模块把模拟输入信号传入功能模块中

    decoder3_8 decoder3_8_inist(
        .in(in),
        .out(out)
    );

    
    initial begin
    $dumpfile("test.vcd"); //生成的vcd文件名称
    $dumpvars(0, tb_decoder3_8); //tb模块名称
    #10000 $finish;
    end
endmodule

test/test.vcd
$date
	Sun Oct  8 15:08:39 2023
$end
$version
	Icarus Verilog
$end
$timescale
	1ns
$end
$scope module tb_decoder3_8 $end
$var wire 8 ! out [7:0] $end
$var reg 3 " in [2:0] $end
$scope module decoder3_8_inist $end
$var wire 3 # in [2:0] $end
$var reg 8 $ out [7:0] $end
$upscope $end
$upscope $end
$enddefinitions $end
#0
$dumpvars
b1 $
b0 #
b0 "
b1 !
$end
#10
b10000 !
b10000 $
b100 "
b100 #
#20
b10 !
b10 $
b1 "
b1 #
#40
b1000 !
b1000 $
b11 "
b11 #
#50
b100000 !
b100000 $
b101 "
b101 #
#80
b100 !
b100 $
b10 "
b10 #
#90
b10 !
b10 $
b1 "
b1 #
#100
b100000 !
b100000 $
b101 "
b101 #
#110
b1000000 !
b1000000 $
b110 "
b110 #
#120
b100000 !
b100000 $
b101 "
b101 #
#140
b10000 !
b10000 $
b100 "
b100 #
#150
b10 !
b10 $
b1 "
b1 #
#160
b1000000 !
b1000000 $
b110 "
b110 #
#170
b100000 !
b100000 $
b101 "
b101 #
#180
b100 !
b100 $
b10 "
b10 #
#190
b100000 !
b100000 $
b101 "
b101 #
#200
b10000000 !
b10000000 $
b111 "
b111 #
#210
b100 !
b100 $
b10 "
b10 #
#220
b10000000 !
b10000000 $
b111 "
b111 #
#230
b100 !
b100 $
b10 "
b10 #
#240
b1000000 !
b1000000 $
b110 "
b110 #
#250
b1 !
b1 $
b0 "
b0 #
#260
b100000 !
b100000 $
b101 "
b101 #
#270
b10000 !
b10000 $
b100 "
b100 #
#280
b100000 !
b100000 $
b101 "
b101 #
#310
b1000 !
b1000 $
b11 "
b11 #
#320
b100 !
b100 $
b10 "
b10 #
#330
b1 !
b1 $
b0 "
b0 #
#350
b100 !
b100 $
b10 "
b10 #
#360
b100000 !
b100000 $
b101 "
b101 #
#370
b1000000 !
b1000000 $
b110 "
b110 #
#380
b1000 !
b1000 $
b11 "
b11 #
#390
b100000 !
b100000 $
b101 "
b101 #
#400
b1000 !
b1000 $
b11 "
b11 #
#420
b100000 !
b100000 $
b101 "
b101 #
#430
b100 !
b100 $
b10 "
b10 #
#440
b1000000 !
b1000000 $
b110 "
b110 #
#450
b100000 !
b100000 $
b101 "
b101 #
#460
b10000000 !
b10000000 $
b111 "
b111 #
#470
b1000 !
b1000 $
b11 "
b11 #
#480
b100 !
b100 $
b10 "
b10 #
#500
b10000 !
b10000 $
b100 "
b100 #
#510
b100 !
b100 $
b10 "
b10 #
#530
b10 !
b10 $
b1 "
b1 #
#540
b1 !
b1 $
b0 "
b0 #
#560
b10 !
b10 $
b1 "
b1 #
#570
b1000 !
b1000 $
b11 "
b11 #
#580
b1000000 !
b1000000 $
b110 "
b110 #
#610
b10000 !
b10000 $
b100 "
b100 #
#620
b100 !
b100 $
b10 "
b10 #
#630
b1000 !
b1000 $
b11 "
b11 #
#640
b10 !
b10 $
b1 "
b1 #
#650
b100000 !
b100000 $
b101 "
b101 #
#660
b10000000 !
b10000000 $
b111 "
b111 #
#670
b1000 !
b1000 $
b11 "
b11 #
#680
b100 !
b100 $
b10 "
b10 #
#690
b1000000 !
b1000000 $
b110 "
b110 #
#700
b100000 !
b100000 $
b101 "
b101 #
#710
b10 !
b10 $
b1 "
b1 #
#730
b100 !
b100 $
b10 "
b10 #
#740
b10000 !
b10000 $
b100 "
b100 #
#750
b10000000 !
b10000000 $
b111 "
b111 #
#770
b1 !
b1 $
b0 "
b0 #
#780
b10000000 !
b10000000 $
b111 "
b111 #
#800
b10000 !
b10000 $
b100 "
b100 #
#810
b1000 !
b1000 $
b11 "
b11 #
#820
b10 !
b10 $
b1 "
b1 #
#840
b1 !
b1 $
b0 "
b0 #
#850
b10000000 !
b10000000 $
b111 "
b111 #
#860
b10 !
b10 $
b1 "
b1 #
#870
b1000000 !
b1000000 $
b110 "
b110 #
#880
b10000 !
b10000 $
b100 "
b100 #
#890
b100 !
b100 $
b10 "
b10 #
#900
b1 !
b1 $
b0 "
b0 #
#910
b10000000 !
b10000000 $
b111 "
b111 #
#920
b100000 !
b100000 $
b101 "
b101 #
#930
b100 !
b100 $
b10 "
b10 #
#940
b1000000 !
b1000000 $
b110 "
b110 #
#950
b100000 !
b100000 $
b101 "
b101 #
#960
b10 !
b10 $
b1 "
b1 #
#970
b10000000 !
b10000000 $
b111 "
b111 #
#980
b1000 !
b1000 $
b11 "
b11 #
#990
b100000 !
b100000 $
b101 "
b101 #
#1000
b1 !
b1 $
b0 "
b0 #
#1010
b1000 !
b1000 $
b11 "
b11 #
#1020
b10 !
b10 $
b1 "
b1 #
#1030
b10000000 !
b10000000 $
b111 "
b111 #
#1040
b100 !
b100 $
b10 "
b10 #
#1050
b1 !
b1 $
b0 "
b0 #
#1060
b1000000 !
b1000000 $
b110 "
b110 #
#1080
b10000 !
b10000 $
b100 "
b100 #
#1090
b100 !
b100 $
b10 "
b10 #
#1100
b1000000 !
b1000000 $
b110 "
b110 #
#1110
b1000 !
b1000 $
b11 "
b11 #
#1130
b10000000 !
b10000000 $
b111 "
b111 #
#1140
b1000 !
b1000 $
b11 "
b11 #
#1150
b10000000 !
b10000000 $
b111 "
b111 #
#1160
b10000 !
b10000 $
b100 "
b100 #
#1170
b10000000 !
b10000000 $
b111 "
b111 #
#1180
b1000 !
b1000 $
b11 "
b11 #
#1190
b1000000 !
b1000000 $
b110 "
b110 #
#1200
b100 !
b100 $
b10 "
b10 #
#1210
b10 !
b10 $
b1 "
b1 #
#1220
b100000 !
b100000 $
b101 "
b101 #
#1230
b100 !
b100 $
b10 "
b10 #
#1240
b100000 !
b100000 $
b101 "
b101 #
#1260
b10000000 !
b10000000 $
b111 "
b111 #
#1270
b10 !
b10 $
b1 "
b1 #
#1280
b10000 !
b10000 $
b100 "
b100 #
#1290
b1 !
b1 $
b0 "
b0 #
#1300
b100 !
b100 $
b10 "
b10 #
#1310
b1000 !
b1000 $
b11 "
b11 #
#1320
b1000000 !
b1000000 $
b110 "
b110 #
#1330
b10000 !
b10000 $
b100 "
b100 #
#1340
b100 !
b100 $
b10 "
b10 #
#1350
b100000 !
b100000 $
b101 "
b101 #
#1360
b1000 !
b1000 $
b11 "
b11 #
#1370
b1000000 !
b1000000 $
b110 "
b110 #
#1390
b10000000 !
b10000000 $
b111 "
b111 #
#1400
b100 !
b100 $
b10 "
b10 #
#1410
b1000000 !
b1000000 $
b110 "
b110 #
#1420
b1 !
b1 $
b0 "
b0 #
#1430
b10 !
b10 $
b1 "
b1 #
#1440
b1 !
b1 $
b0 "
b0 #
#1450
b10000 !
b10000 $
b100 "
b100 #
#1460
b1000 !
b1000 $
b11 "
b11 #
#1470
b10000 !
b10000 $
b100 "
b100 #
#1480
b10 !
b10 $
b1 "
b1 #
#1490
b1000 !
b1000 $
b11 "
b11 #
#1500
b100000 !
b100000 $
b101 "
b101 #
#1510
b10 !
b10 $
b1 "
b1 #
#1520
b100000 !
b100000 $
b101 "
b101 #
#1530
b1000000 !
b1000000 $
b110 "
b110 #
#1540
b100 !
b100 $
b10 "
b10 #
#1550
b1000000 !
b1000000 $
b110 "
b110 #
#1560
b100000 !
b100000 $
b101 "
b101 #
#1570
b1000000 !
b1000000 $
b110 "
b110 #
#1580
b10000 !
b10000 $
b100 "
b100 #
#1590
b10000000 !
b10000000 $
b111 "
b111 #
#1600
b10 !
b10 $
b1 "
b1 #
#1610
b10000 !
b10000 $
b100 "
b100 #
#1620
b1 !
b1 $
b0 "
b0 #
#1640
b100000 !
b100000 $
b101 "
b101 #
#1650
b10000000 !
b10000000 $
b111 "
b111 #
#1660
b1000000 !
b1000000 $
b110 "
b110 #
#1670
b1 !
b1 $
b0 "
b0 #
#1680
b10000 !
b10000 $
b100 "
b100 #
#1690
b100000 !
b100000 $
b101 "
b101 #
#1700
b10 !
b10 $
b1 "
b1 #
#1710
b10000 !
b10000 $
b100 "
b100 #
#1720
b1000000 !
b1000000 $
b110 "
b110 #
#1730
b100 !
b100 $
b10 "
b10 #
#1740
b100000 !
b100000 $
b101 "
b101 #
#1750
b1000000 !
b1000000 $
b110 "
b110 #
#1760
b1 !
b1 $
b0 "
b0 #
#1770
b1000 !
b1000 $
b11 "
b11 #
#1780
b100 !
b100 $
b10 "
b10 #
#1790
b1000000 !
b1000000 $
b110 "
b110 #
#1800
b100 !
b100 $
b10 "
b10 #
#1810
b100000 !
b100000 $
b101 "
b101 #
#1820
b100 !
b100 $
b10 "
b10 #
#1830
b10 !
b10 $
b1 "
b1 #
#1840
b10000000 !
b10000000 $
b111 "
b111 #
#1850
b1000000 !
b1000000 $
b110 "
b110 #
#1860
b1 !
b1 $
b0 "
b0 #
#1870
b1000000 !
b1000000 $
b110 "
b110 #
#1890
b100000 !
b100000 $
b101 "
b101 #
#1900
b10000 !
b10000 $
b100 "
b100 #
#1910
b1000000 !
b1000000 $
b110 "
b110 #
#1920
b1 !
b1 $
b0 "
b0 #
#1930
b1000000 !
b1000000 $
b110 "
b110 #
#1940
b1000 !
b1000 $
b11 "
b11 #
#1950
b10000000 !
b10000000 $
b111 "
b111 #
#1960
b10 !
b10 $
b1 "
b1 #
#1970
b100 !
b100 $
b10 "
b10 #
#1980
b10 !
b10 $
b1 "
b1 #
#1990
b10000000 !
b10000000 $
b111 "
b111 #
#2000
b10 !
b10 $
b1 "
b1 #
#2010
b1000000 !
b1000000 $
b110 "
b110 #
#2020
b1 !
b1 $
b0 "
b0 #
#2030
b100000 !
b100000 $
b101 "
b101 #
#2050
b10 !
b10 $
b1 "
b1 #
#2070
b100000 !
b100000 $
b101 "
b101 #
#2080
b1 !
b1 $
b0 "
b0 #
#2090
b1000 !
b1000 $
b11 "
b11 #
#2110
b10000 !
b10000 $
b100 "
b100 #
#2120
b100 !
b100 $
b10 "
b10 #
#2130
b1000000 !
b1000000 $
b110 "
b110 #
#2140
b1 !
b1 $
b0 "
b0 #
#2150
b10 !
b10 $
b1 "
b1 #
#2170
b1000000 !
b1000000 $
b110 "
b110 #
#2190
b10000000 !
b10000000 $
b111 "
b111 #
#2200
b100 !
b100 $
b10 "
b10 #
#2220
b100000 !
b100000 $
b101 "
b101 #
#2230
b1000000 !
b1000000 $
b110 "
b110 #
#2240
b1 !
b1 $
b0 "
b0 #
#2250
b10 !
b10 $
b1 "
b1 #
#2260
b1 !
b1 $
b0 "
b0 #
#2270
b100 !
b100 $
b10 "
b10 #
#2280
b1000 !
b1000 $
b11 "
b11 #
#2300
b10000000 !
b10000000 $
b111 "
b111 #
#2310
b1000000 !
b1000000 $
b110 "
b110 #
#2320
b100 !
b100 $
b10 "
b10 #
#2330
b10000 !
b10000 $
b100 "
b100 #
#2340
b10 !
b10 $
b1 "
b1 #
#2350
b100 !
b100 $
b10 "
b10 #
#2360
b10000 !
b10000 $
b100 "
b100 #
#2370
b10000000 !
b10000000 $
b111 "
b111 #
#2380
b1000000 !
b1000000 $
b110 "
b110 #
#2390
b100 !
b100 $
b10 "
b10 #
#2420
b100000 !
b100000 $
b101 "
b101 #
#2430
b10000 !
b10000 $
b100 "
b100 #
#2450
b100 !
b100 $
b10 "
b10 #
#2460
b10 !
b10 $
b1 "
b1 #
#2480
b1000000 !
b1000000 $
b110 "
b110 #
#2490
b1000 !
b1000 $
b11 "
b11 #
#2510
b10000000 !
b10000000 $
b111 "
b111 #
#2520
b10 !
b10 $
b1 "
b1 #
#2530
b1000000 !
b1000000 $
b110 "
b110 #
#2540
b100000 !
b100000 $
b101 "
b101 #
#2550
b10000000 !
b10000000 $
b111 "
b111 #
#2560
b1000 !
b1000 $
b11 "
b11 #
#2570
b1 !
b1 $
b0 "
b0 #
#2580
b1000000 !
b1000000 $
b110 "
b110 #
#2590
b1000 !
b1000 $
b11 "
b11 #
#2600
b100 !
b100 $
b10 "
b10 #
#2610
b1 !
b1 $
b0 "
b0 #
#2620
b100000 !
b100000 $
b101 "
b101 #
#2630
b1000 !
b1000 $
b11 "
b11 #
#2640
b100 !
b100 $
b10 "
b10 #
#2650
b1000000 !
b1000000 $
b110 "
b110 #
#2660
b100000 !
b100000 $
b101 "
b101 #
#2670
b10000 !
b10000 $
b100 "
b100 #
#2680
b1 !
b1 $
b0 "
b0 #
#2690
b10 !
b10 $
b1 "
b1 #
#2700
b1000000 !
b1000000 $
b110 "
b110 #
#2710
b10 !
b10 $
b1 "
b1 #
#2720
b1000 !
b1000 $
b11 "
b11 #
#2730
b1 !
b1 $
b0 "
b0 #
#2740
b1000 !
b1000 $
b11 "
b11 #
#2750
b1000000 !
b1000000 $
b110 "
b110 #
#2760
b1000 !
b1000 $
b11 "
b11 #
#2770
b100 !
b100 $
b10 "
b10 #
#2780
b10000 !
b10000 $
b100 "
b100 #
#2790
b1000 !
b1000 $
b11 "
b11 #
#2800
b1 !
b1 $
b0 "
b0 #
#2810
b100 !
b100 $
b10 "
b10 #
#2820
b1 !
b1 $
b0 "
b0 #
#2830
b10 !
b10 $
b1 "
b1 #
#2840
b100000 !
b100000 $
b101 "
b101 #
#2850
b10 !
b10 $
b1 "
b1 #
#2860
b1000 !
b1000 $
b11 "
b11 #
#2870
b10 !
b10 $
b1 "
b1 #
#2880
b1 !
b1 $
b0 "
b0 #
#2890
b10000000 !
b10000000 $
b111 "
b111 #
#2900
b10 !
b10 $
b1 "
b1 #
#2910
b10000000 !
b10000000 $
b111 "
b111 #
#2920
b10000 !
b10000 $
b100 "
b100 #
#2930
b1 !
b1 $
b0 "
b0 #
#2940
b1000000 !
b1000000 $
b110 "
b110 #
#2950
b10000 !
b10000 $
b100 "
b100 #
#2960
b100 !
b100 $
b10 "
b10 #
#2970
b1000000 !
b1000000 $
b110 "
b110 #
#2980
b10 !
b10 $
b1 "
b1 #
#2990
b100000 !
b100000 $
b101 "
b101 #
#3010
b1000 !
b1000 $
b11 "
b11 #
#3020
b100000 !
b100000 $
b101 "
b101 #
#3040
b10000000 !
b10000000 $
b111 "
b111 #
#3050
b10000 !
b10000 $
b100 "
b100 #
#3060
b10000000 !
b10000000 $
b111 "
b111 #
#3080
b10 !
b10 $
b1 "
b1 #
#3100
b1000 !
b1000 $
b11 "
b11 #
#3110
b10 !
b10 $
b1 "
b1 #
#3140
b100 !
b100 $
b10 "
b10 #
#3160
b100000 !
b100000 $
b101 "
b101 #
#3170
b1000 !
b1000 $
b11 "
b11 #
#3180
b10000 !
b10000 $
b100 "
b100 #
#3190
b100 !
b100 $
b10 "
b10 #
#3200
b1000000 !
b1000000 $
b110 "
b110 #
#3210
b1 !
b1 $
b0 "
b0 #
#3220
b10000000 !
b10000000 $
b111 "
b111 #
#3230
b1000000 !
b1000000 $
b110 "
b110 #
#3240
b1 !
b1 $
b0 "
b0 #
#3280
b1000000 !
b1000000 $
b110 "
b110 #
#3290
b100000 !
b100000 $
b101 "
b101 #
#3300
b1 !
b1 $
b0 "
b0 #
#3310
b10000 !
b10000 $
b100 "
b100 #
#3320
b10 !
b10 $
b1 "
b1 #
#3330
b1 !
b1 $
b0 "
b0 #
#3340
b10000 !
b10000 $
b100 "
b100 #
#3350
b100 !
b100 $
b10 "
b10 #
#3370
b100000 !
b100000 $
b101 "
b101 #
#3380
b10 !
b10 $
b1 "
b1 #
#3390
b10000000 !
b10000000 $
b111 "
b111 #
#3400
b1000 !
b1000 $
b11 "
b11 #
#3410
b10 !
b10 $
b1 "
b1 #
#3420
b1000000 !
b1000000 $
b110 "
b110 #
#3430
b100000 !
b100000 $
b101 "
b101 #
#3440
b10 !
b10 $
b1 "
b1 #
#3450
b100000 !
b100000 $
b101 "
b101 #
#3460
b100 !
b100 $
b10 "
b10 #
#3470
b10000000 !
b10000000 $
b111 "
b111 #
#3480
b10000 !
b10000 $
b100 "
b100 #
#3500
b10 !
b10 $
b1 "
b1 #
#3510
b1000 !
b1000 $
b11 "
b11 #
#3520
b1000000 !
b1000000 $
b110 "
b110 #
#3530
b10000000 !
b10000000 $
b111 "
b111 #
#3540
b1000000 !
b1000000 $
b110 "
b110 #
#3550
b10000 !
b10000 $
b100 "
b100 #
#3560
b100000 !
b100000 $
b101 "
b101 #
#3570
b1 !
b1 $
b0 "
b0 #
#3590
b100 !
b100 $
b10 "
b10 #
#3600
b10000 !
b10000 $
b100 "
b100 #
#3610
b100000 !
b100000 $
b101 "
b101 #
#3630
b1000 !
b1000 $
b11 "
b11 #
#3640
b10 !
b10 $
b1 "
b1 #
#3650
b1000000 !
b1000000 $
b110 "
b110 #
#3660
b100000 !
b100000 $
b101 "
b101 #
#3670
b1000 !
b1000 $
b11 "
b11 #
#3680
b10000000 !
b10000000 $
b111 "
b111 #
#3690
b1000 !
b1000 $
b11 "
b11 #
#3710
b100000 !
b100000 $
b101 "
b101 #
#3720
b10 !
b10 $
b1 "
b1 #
#3730
b10000 !
b10000 $
b100 "
b100 #
#3740
b100000 !
b100000 $
b101 "
b101 #
#3750
b1 !
b1 $
b0 "
b0 #
#3760
b100000 !
b100000 $
b101 "
b101 #
#3770
b100 !
b100 $
b10 "
b10 #
#3780
b1 !
b1 $
b0 "
b0 #
#3790
b100000 !
b100000 $
b101 "
b101 #
#3800
b100 !
b100 $
b10 "
b10 #
#3810
b10000 !
b10000 $
b100 "
b100 #
#3820
b1000000 !
b1000000 $
b110 "
b110 #
#3830
b10000 !
b10000 $
b100 "
b100 #
#3840
b1 !
b1 $
b0 "
b0 #
#3850
b10000000 !
b10000000 $
b111 "
b111 #
#3860
b100 !
b100 $
b10 "
b10 #
#3870
b10000 !
b10000 $
b100 "
b100 #
#3880
b100 !
b100 $
b10 "
b10 #
#3890
b10000 !
b10000 $
b100 "
b100 #
#3900
b1 !
b1 $
b0 "
b0 #
#3910
b100 !
b100 $
b10 "
b10 #
#3920
b1000 !
b1000 $
b11 "
b11 #
#3930
b1000000 !
b1000000 $
b110 "
b110 #
#3940
b100000 !
b100000 $
b101 "
b101 #
#3950
b100 !
b100 $
b10 "
b10 #
#3970
b10 !
b10 $
b1 "
b1 #
#3980
b10000 !
b10000 $
b100 "
b100 #
#3990
b100000 !
b100000 $
b101 "
b101 #
#4000
b1000 !
b1000 $
b11 "
b11 #
#4010
b10000 !
b10000 $
b100 "
b100 #
#4020
b10000000 !
b10000000 $
b111 "
b111 #
#4030
b1000000 !
b1000000 $
b110 "
b110 #
#4040
b10 !
b10 $
b1 "
b1 #
#4050
b10000 !
b10000 $
b100 "
b100 #
#4060
b1 !
b1 $
b0 "
b0 #
#4070
b10000 !
b10000 $
b100 "
b100 #
#4090
b10000000 !
b10000000 $
b111 "
b111 #
#4100
b100 !
b100 $
b10 "
b10 #
#4110
b10 !
b10 $
b1 "
b1 #
#4120
b1 !
b1 $
b0 "
b0 #
#4130
b1000 !
b1000 $
b11 "
b11 #
#4150
b10000 !
b10000 $
b100 "
b100 #
#4160
b1000 !
b1000 $
b11 "
b11 #
#4170
b10000 !
b10000 $
b100 "
b100 #
#4180
b10 !
b10 $
b1 "
b1 #
#4200
b10000000 !
b10000000 $
b111 "
b111 #
#4210
b10000 !
b10000 $
b100 "
b100 #
#4220
b10000000 !
b10000000 $
b111 "
b111 #
#4230
b100000 !
b100000 $
b101 "
b101 #
#4240
b1 !
b1 $
b0 "
b0 #
#4250
b100 !
b100 $
b10 "
b10 #
#4260
b10 !
b10 $
b1 "
b1 #
#4280
b1 !
b1 $
b0 "
b0 #
#4290
b10000 !
b10000 $
b100 "
b100 #
#4300
b1000 !
b1000 $
b11 "
b11 #
#4320
b100 !
b100 $
b10 "
b10 #
#4330
b1 !
b1 $
b0 "
b0 #
#4340
b100000 !
b100000 $
b101 "
b101 #
#4350
b100 !
b100 $
b10 "
b10 #
#4360
b10000 !
b10000 $
b100 "
b100 #
#4370
b1000 !
b1000 $
b11 "
b11 #
#4380
b10 !
b10 $
b1 "
b1 #
#4390
b100 !
b100 $
b10 "
b10 #
#4410
b10 !
b10 $
b1 "
b1 #
#4420
b1 !
b1 $
b0 "
b0 #
#4430
b1000000 !
b1000000 $
b110 "
b110 #
#4440
b10000000 !
b10000000 $
b111 "
b111 #
#4450
b1000 !
b1000 $
b11 "
b11 #
#4460
b1000000 !
b1000000 $
b110 "
b110 #
#4470
b1000 !
b1000 $
b11 "
b11 #
#4480
b1 !
b1 $
b0 "
b0 #
#4490
b10000000 !
b10000000 $
b111 "
b111 #
#4500
b10 !
b10 $
b1 "
b1 #
#4510
b10000 !
b10000 $
b100 "
b100 #
#4520
b10 !
b10 $
b1 "
b1 #
#4530
b100000 !
b100000 $
b101 "
b101 #
#4540
b10000000 !
b10000000 $
b111 "
b111 #
#4550
b1 !
b1 $
b0 "
b0 #
#4560
b10 !
b10 $
b1 "
b1 #
#4580
b10000000 !
b10000000 $
b111 "
b111 #
#4590
b100 !
b100 $
b10 "
b10 #
#4600
b1 !
b1 $
b0 "
b0 #
#4610
b1000 !
b1000 $
b11 "
b11 #
#4620
b10000 !
b10000 $
b100 "
b100 #
#4630
b1 !
b1 $
b0 "
b0 #
#4640
b10000000 !
b10000000 $
b111 "
b111 #
#4650
b1000000 !
b1000000 $
b110 "
b110 #
#4660
b1 !
b1 $
b0 "
b0 #
#4670
b10000000 !
b10000000 $
b111 "
b111 #
#4680
b100000 !
b100000 $
b101 "
b101 #
#4690
b10000 !
b10000 $
b100 "
b100 #
#4700
b10000000 !
b10000000 $
b111 "
b111 #
#4710
b1000000 !
b1000000 $
b110 "
b110 #
#4720
b10 !
b10 $
b1 "
b1 #
#4730
b1000 !
b1000 $
b11 "
b11 #
#4740
b10 !
b10 $
b1 "
b1 #
#4750
b1000 !
b1000 $
b11 "
b11 #
#4760
b1 !
b1 $
b0 "
b0 #
#4770
b100 !
b100 $
b10 "
b10 #
#4780
b100000 !
b100000 $
b101 "
b101 #
#4790
b1 !
b1 $
b0 "
b0 #
#4800
b10000000 !
b10000000 $
b111 "
b111 #
#4810
b1000000 !
b1000000 $
b110 "
b110 #
#4820
b10000000 !
b10000000 $
b111 "
b111 #
#4830
b10 !
b10 $
b1 "
b1 #
#4840
b1 !
b1 $
b0 "
b0 #
#4850
b1000000 !
b1000000 $
b110 "
b110 #
#4860
b10000000 !
b10000000 $
b111 "
b111 #
#4870
b10 !
b10 $
b1 "
b1 #
#4880
b100000 !
b100000 $
b101 "
b101 #
#4890
b1000000 !
b1000000 $
b110 "
b110 #
#4900
b1 !
b1 $
b0 "
b0 #
#4910
b100000 !
b100000 $
b101 "
b101 #
#4920
b1 !
b1 $
b0 "
b0 #
#4930
b10000 !
b10000 $
b100 "
b100 #
#4940
b10 !
b10 $
b1 "
b1 #
#4960
b10000000 !
b10000000 $
b111 "
b111 #
#4970
b1000000 !
b1000000 $
b110 "
b110 #
#4980
b10 !
b10 $
b1 "
b1 #
#4990
b100000 !
b100000 $
b101 "
b101 #
#5000
b1 !
b1 $
b0 "
b0 #
#5020
b100 !
b100 $
b10 "
b10 #
#5030
b10000000 !
b10000000 $
b111 "
b111 #
#5040
b10 !
b10 $
b1 "
b1 #
#5050
b100000 !
b100000 $
b101 "
b101 #
#5060
b1000000 !
b1000000 $
b110 "
b110 #
#5070
b100 !
b100 $
b10 "
b10 #
#5080
b10000 !
b10000 $
b100 "
b100 #
#5090
b10 !
b10 $
b1 "
b1 #
#5100
b10000000 !
b10000000 $
b111 "
b111 #
#5110
b1000 !
b1000 $
b11 "
b11 #
#5120
b10000000 !
b10000000 $
b111 "
b111 #
#5130
b100 !
b100 $
b10 "
b10 #
#5140
b10 !
b10 $
b1 "
b1 #
#5150
b1000 !
b1000 $
b11 "
b11 #
#5170
b100000 !
b100000 $
b101 "
b101 #
#5180
b10 !
b10 $
b1 "
b1 #
#5190
b10000000 !
b10000000 $
b111 "
b111 #
#5200
b10 !
b10 $
b1 "
b1 #
#5210
b100 !
b100 $
b10 "
b10 #
#5220
b10 !
b10 $
b1 "
b1 #
#5230
b100 !
b100 $
b10 "
b10 #
#5240
b10000 !
b10000 $
b100 "
b100 #
#5250
b100 !
b100 $
b10 "
b10 #
#5260
b100000 !
b100000 $
b101 "
b101 #
#5270
b10 !
b10 $
b1 "
b1 #
#5280
b100000 !
b100000 $
b101 "
b101 #
#5300
b10 !
b10 $
b1 "
b1 #
#5320
b10000000 !
b10000000 $
b111 "
b111 #
#5330
b1000 !
b1000 $
b11 "
b11 #
#5340
b100000 !
b100000 $
b101 "
b101 #
#5350
b1 !
b1 $
b0 "
b0 #
#5360
b1000000 !
b1000000 $
b110 "
b110 #
#5370
b100 !
b100 $
b10 "
b10 #
#5380
b100000 !
b100000 $
b101 "
b101 #
#5390
b100 !
b100 $
b10 "
b10 #
#5400
b10000 !
b10000 $
b100 "
b100 #
#5410
b1 !
b1 $
b0 "
b0 #
#5420
b1000 !
b1000 $
b11 "
b11 #
#5430
b100000 !
b100000 $
b101 "
b101 #
#5440
b1 !
b1 $
b0 "
b0 #
#5450
b1000000 !
b1000000 $
b110 "
b110 #
#5460
b10000 !
b10000 $
b100 "
b100 #
#5470
b1000 !
b1000 $
b11 "
b11 #
#5480
b10 !
b10 $
b1 "
b1 #
#5490
b1 !
b1 $
b0 "
b0 #
#5500
b1000 !
b1000 $
b11 "
b11 #
#5510
b1000000 !
b1000000 $
b110 "
b110 #
#5520
b1000 !
b1000 $
b11 "
b11 #
#5530
b10000 !
b10000 $
b100 "
b100 #
#5540
b1000000 !
b1000000 $
b110 "
b110 #
#5550
b10000 !
b10000 $
b100 "
b100 #
#5560
b10 !
b10 $
b1 "
b1 #
#5580
b1000 !
b1000 $
b11 "
b11 #
#5590
b10000 !
b10000 $
b100 "
b100 #
#5600
b100000 !
b100000 $
b101 "
b101 #
#5610
b10000 !
b10000 $
b100 "
b100 #
#5620
b10 !
b10 $
b1 "
b1 #
#5630
b100 !
b100 $
b10 "
b10 #
#5640
b100000 !
b100000 $
b101 "
b101 #
#5660
b1000000 !
b1000000 $
b110 "
b110 #
#5670
b100 !
b100 $
b10 "
b10 #
#5680
b1 !
b1 $
b0 "
b0 #
#5700
b100000 !
b100000 $
b101 "
b101 #
#5710
b10000000 !
b10000000 $
b111 "
b111 #
#5720
b1 !
b1 $
b0 "
b0 #
#5740
b100000 !
b100000 $
b101 "
b101 #
#5750
b10000 !
b10000 $
b100 "
b100 #
#5760
b1000 !
b1000 $
b11 "
b11 #
#5770
b1 !
b1 $
b0 "
b0 #
#5780
b100000 !
b100000 $
b101 "
b101 #
#5800
b1 !
b1 $
b0 "
b0 #
#5810
b100000 !
b100000 $
b101 "
b101 #
#5820
b10 !
b10 $
b1 "
b1 #
#5830
b10000 !
b10000 $
b100 "
b100 #
#5840
b1 !
b1 $
b0 "
b0 #
#5870
b10 !
b10 $
b1 "
b1 #
#5880
b100000 !
b100000 $
b101 "
b101 #
#5920
b10000 !
b10000 $
b100 "
b100 #
#5930
b100 !
b100 $
b10 "
b10 #
#5940
b10000 !
b10000 $
b100 "
b100 #
#5950
b1 !
b1 $
b0 "
b0 #
#5960
b1000000 !
b1000000 $
b110 "
b110 #
#5970
b100 !
b100 $
b10 "
b10 #
#5980
b1000000 !
b1000000 $
b110 "
b110 #
#5990
b10000000 !
b10000000 $
b111 "
b111 #
#6000
b1000 !
b1000 $
b11 "
b11 #
#6010
b100000 !
b100000 $
b101 "
b101 #
#6020
b10000000 !
b10000000 $
b111 "
b111 #
#6030
b100000 !
b100000 $
b101 "
b101 #
#6040
b1000 !
b1000 $
b11 "
b11 #
#6050
b10 !
b10 $
b1 "
b1 #
#6060
b1000000 !
b1000000 $
b110 "
b110 #
#6070
b1 !
b1 $
b0 "
b0 #
#6080
b1000000 !
b1000000 $
b110 "
b110 #
#6090
b1 !
b1 $
b0 "
b0 #
#6100
b100 !
b100 $
b10 "
b10 #
#6110
b10000 !
b10000 $
b100 "
b100 #
#6120
b10 !
b10 $
b1 "
b1 #
#6130
b1000 !
b1000 $
b11 "
b11 #
#6140
b1 !
b1 $
b0 "
b0 #
#6150
b10000000 !
b10000000 $
b111 "
b111 #
#6160
b1 !
b1 $
b0 "
b0 #
#6170
b100000 !
b100000 $
b101 "
b101 #
#6190
b1000 !
b1000 $
b11 "
b11 #
#6200
b10000 !
b10000 $
b100 "
b100 #
#6230
b10 !
b10 $
b1 "
b1 #
#6240
b100000 !
b100000 $
b101 "
b101 #
#6250
b1000000 !
b1000000 $
b110 "
b110 #
#6260
b1000 !
b1000 $
b11 "
b11 #
#6270
b1 !
b1 $
b0 "
b0 #
#6280
b10000 !
b10000 $
b100 "
b100 #
#6300
b1000000 !
b1000000 $
b110 "
b110 #
#6310
b100 !
b100 $
b10 "
b10 #
#6320
b1 !
b1 $
b0 "
b0 #
#6330
b100000 !
b100000 $
b101 "
b101 #
