CLA_4/CAL_4.v
module CAL_4(
    input[3:0] X,
    input[3:0] Y,
    input[0:0] Cin,
    output[3:0] S,
    output[0:0] Cout
);
    wire[3:0] P=X|Y;
    wire[3:0] G=X&Y;
    wire[3:0] Gn=~G;

    and i1(P0Gn0,P[0],Gn[0]);
    xor(S[0],P0Gn0,Cin);
    nand(P0Cin0,P[0],Cin);
    nand(Cout0,Gn[0],P0Cin0);

    and(P1Gn1,P[1],Gn[1]);
    xor(S[1],P1Gn1,Cout0);
    nand(P1P0Cin0,P[1],P[0],Cin);
    nand(P1G0,P[1],G[0]);
    nand(Cout1,Gn[1],P1G0,P1P0Cin0);

    and(P2Gn2,P[2],Gn[2]);
    xor(S[2],P2Gn2,Cout1);
    nand(P2P1P0Cin0,P[2],P[1],P[0],Cin);
    nand(P2P1G0,P[2],P[1],G[0]);
    nand(P2G1,P[2],G[1]);
    nand(Cout2,Gn[2],P2G1,P2P1G0,P2P1P0Cin0);

    and(P3Gn3,P[3],Gn[3]);
    xor(S[3],P3Gn3,Cout2);
    nand(P3P2P1P0Cin0,P[3],P[2],P[1],P[0],Cin);
    nand(P3P2P1G0,P[3],P[2],P[1],G[0]);
    nand(P3P2G1,P[3],P[2],G[1]);
    nand(P3G2,P[3],G[2]);
    nand(Cout,Gn[3],P3G2,P3P2G1,P3P2P1G0,P3P2P1P0Cin0);

endmodule

CLA_4/CAL_4_tb.v
`timescale 1ns/1ns
`include"CAL_4.v"
module tb_CAL_4();
    reg[3:0] X,Y;
    reg Cin=0;
    integer j;
    initial begin
        for(j=0;j<15;j++)begin
            X=j;
            Y=16'hF-2*j;
            #100;
        end
    end

    CAL_4 data(
        .X(X),
        .Y(Y),
        .Cin(Cin)
    );
    initial begin
        $dumpfile("CAL_4.vcd");
        $dumpvars(0,tb_CAL_4);
        #10000 $finish;
    end
endmodule

CLA_4/CAL_4.vcd
$date
	Sun Oct 29 09:53:42 2023
$end
$version
	Icarus Verilog
$end
$timescale
	1ns
$end
$scope module tb_CAL_4 $end
$var reg 1 ! Cin $end
$var reg 4 " X [3:0] $end
$var reg 4 # Y [3:0] $end
$var integer 32 $ j [31:0] $end
$scope module data $end
$var wire 1 ! Cin $end
$var wire 1 % Cout $end
$var wire 1 & Cout0 $end
$var wire 1 ' Cout1 $end
$var wire 1 ( Cout2 $end
$var wire 4 ) G [3:0] $end
$var wire 4 * Gn [3:0] $end
$var wire 4 + P [3:0] $end
$var wire 1 , P0Cin0 $end
$var wire 1 - P0Gn0 $end
$var wire 1 . P1G0 $end
$var wire 1 / P1Gn1 $end
$var wire 1 0 P1P0Cin0 $end
$var wire 1 1 P2G1 $end
$var wire 1 2 P2Gn2 $end
$var wire 1 3 P2P1G0 $end
$var wire 1 4 P2P1P0Cin0 $end
$var wire 1 5 P3G2 $end
$var wire 1 6 P3Gn3 $end
$var wire 1 7 P3P2G1 $end
$var wire 1 8 P3P2P1G0 $end
$var wire 1 9 P3P2P1P0Cin0 $end
$var wire 4 : X [3:0] $end
$var wire 4 ; Y [3:0] $end
$var wire 4 < S [3:0] $end
$upscope $end
$upscope $end
$enddefinitions $end
#0
$dumpvars
b1111 <
b1111 ;
b0 :
19
18
17
16
15
14
13
12
11
10
1/
1.
1-
1,
b1111 +
b1111 *
b0 )
0(
0'
0&
0%
b0 $
b1111 #
b0 "
0!
$end
#100
b1110 <
0-
1&
0/
b1110 *
b1101 +
b1 )
b1101 #
b1101 ;
b1 "
b1 :
b1 $
#200
b1101 <
1-
0&
1'
02
b1101 *
b1011 +
b10 )
b1011 #
b1011 ;
b10 "
b10 :
b10 $
#300
b1100 <
0-
1&
1/
0.
b1110 *
b1 )
b1001 #
b1001 ;
b11 "
b11 :
b11 $
#400
b1011 <
1-
0&
1(
0'
06
1.
b1011 *
b111 +
b100 )
b111 #
b111 ;
b100 "
b100 :
b100 $
#500
b1010 <
0-
1&
0/
b1010 *
b101 +
b101 )
b101 #
b101 ;
b101 "
b101 :
b101 $
#600
b1001 <
1-
0&
1'
12
01
b1101 *
b111 +
b10 )
b11 #
b11 ;
b110 "
b110 :
b110 $
#700
b1000 <
0-
1&
1/
0.
03
11
b1110 *
b1 )
b1 #
b1 ;
b111 "
b111 :
b111 $
#800
1%
b111 <
1-
0&
0'
0(
1.
13
b111 *
b1111 +
b1000 )
b1111 #
b1111 ;
b1000 "
b1000 :
b1000 $
#900
b110 <
0-
1&
0/
b110 *
b1101 +
b1001 )
b1101 #
b1101 ;
b1001 "
b1001 :
b1001 $
#1000
b101 <
1-
0&
1'
02
b101 *
b1011 +
b1010 )
b1011 #
b1011 ;
b1010 "
b1010 :
b1010 $
#1100
b100 <
0-
1&
1/
0.
b110 *
b1001 )
b1001 #
b1001 ;
b1011 "
b1011 :
b1011 $
#1200
b11 <
1-
0&
1(
16
0'
1.
05
b1011 *
b1111 +
b100 )
b111 #
b111 ;
b1100 "
b1100 :
b1100 $
#1300
b10 <
0-
1&
0/
b1010 *
b1101 +
b101 )
b101 #
b101 ;
b1101 "
b1101 :
b1101 $
#1400
b1 <
1-
0&
1'
12
01
07
15
b1101 *
b1111 +
b10 )
b11 #
b11 ;
b1110 "
b1110 :
b1110 $
#1500
b1111 $
