CPU-with-Exception-Interrupt/D_Latch.v
`ifndef D_LATCH_V
`define D_LATCH_V

module D_Latch(
    input D,
    input En,
    output Q,
    output Qn
);
    wire Sn, Rn, Dn;
    not  i0 (Dn, D);
    nand i1 (Sn, D, En);
    nand i2 (Rn, En, Dn);
    nand i3 (Q, Sn, Qn);
    nand i4 (Qn, Q, Rn); 
endmodule

`endif

REGFILE/D_FF.v
`ifndef D_FF_V
`define D_FF_V

`include "REGFILE/D_Latch.v"
module D_FF (
    input D,
    input Clk,
    output Q,
    output Qn
);
    wire Clkn, Q0, Qn0;
    not i0 (Clkn, Clk);
    D_Latch d0 (D, Clkn, Q0, Qn0); //主锁存器
    D_Latch d1 (Q0, Clk, Q, Qn); //从锁存器
endmodule

`endif

REGFILE/tb_D_FF.v
`include "D_FF.v"
`timescale 1ns/1ns

module tb_D_FF();
    reg D,Clk;
    wire Q,Qn;

    always #30 Clk = ~Clk;
        initial begin
            Clk = 0;
            D = 1;
            #50;
            D = 0;
            #50;
            D = 1;
        end

    D_FF D_FF_test(
        .D(D),
        .Clk(Clk),
        .Q(Q),
        .Qn(Qn)
    );
    initial begin
      $dumpfile("D_FF.vcd");
      $dumpvars(0,tb_D_FF);
      #10000 $finish;
    end
 endmodule

REGFILE/D_FF.vcd
$date
	Tue Oct 31 05:39:03 2023
$end
$version
	Icarus Verilog
$end
$timescale
	1ns
$end
$scope module tb_D_FF $end
$var wire 1 ! Qn $end
$var wire 1 " Q $end
$var reg 1 # Clk $end
$var reg 1 $ D $end
$scope module D_FF_test $end
$var wire 1 # Clk $end
$var wire 1 % Clkn $end
$var wire 1 $ D $end
$var wire 1 & Qn0 $end
$var wire 1 ! Qn $end
$var wire 1 ' Q0 $end
$var wire 1 " Q $end
$scope module d0 $end
$var wire 1 $ D $end
$var wire 1 ( Dn $end
$var wire 1 % En $end
$var wire 1 ' Q $end
$var wire 1 & Qn $end
$var wire 1 ) Rn $end
$var wire 1 * Sn $end
$upscope $end
$scope module d1 $end
$var wire 1 ' D $end
$var wire 1 + Dn $end
$var wire 1 # En $end
$var wire 1 " Q $end
$var wire 1 ! Qn $end
$var wire 1 , Rn $end
$var wire 1 - Sn $end
$upscope $end
$upscope $end
$upscope $end
$enddefinitions $end
#0
$dumpvars
1-
1,
0+
0*
1)
0(
1'
0&
1%
1$
0#
x"
x!
$end
#30
0!
1*
1"
0%
0-
1#
#50
1(
0$
#60
1+
0'
1&
0)
1%
1-
0#
#90
0"
1)
1!
0%
0,
1#
#100
0(
1$
#120
0&
0+
1'
0*
1%
1,
0#
#150
0!
1*
1"
0%
0-
1#
#180
0*
1%
1-
0#
#210
1*
0%
0-
1#
#240
0*
1%
1-
0#
#270
1*
0%
0-
1#
#300
0*
1%
1-
0#
#330
1*
0%
0-
1#
#360
0*
1%
1-
0#
#390
1*
0%
0-
1#
#420
0*
1%
1-
0#
#450
1*
0%
0-
1#
#480
0*
1%
1-
0#
#510
1*
0%
0-
1#
#540
0*
1%
1-
0#
#570
1*
0%
0-
1#
#600
0*
1%
1-
0#
#630
1*
0%
0-
1#
#660
0*
1%
1-
0#
#690
1*
0%
0-
1#
#720
0*
1%
1-
0#
#750
1*
0%
0-
1#
#780
0*
1%
1-
0#
#810
1*
0%
0-
1#
#840
0*
1%
1-
0#
#870
1*
0%
0-
1#
#900
0*
1%
1-
0#
#930
1*
0%
0-
1#
#960
0*
1%
1-
0#
#990
1*
0%
0-
1#
#1020
0*
1%
1-
0#
#1050
1*
0%
0-
1#
#1080
0*
1%
1-
0#
#1110
1*
0%
0-
1#
#1140
0*
1%
1-
0#
#1170
1*
0%
0-
1#
#1200
0*
1%
1-
0#
#1230
1*
0%
0-
1#
#1260
0*
1%
1-
0#
#1290
1*
0%
0-
1#
#1320
0*
1%
1-
0#
#1350
1*
0%
0-
1#
#1380
0*
1%
1-
0#
#1410
1*
0%
0-
1#
#1440
0*
1%
1-
0#
#1470
1*
0%
0-
1#
#1500
0*
1%
1-
0#
#1530
1*
0%
0-
1#
#1560
0*
1%
1-
0#
#1590
1*
0%
0-
1#
#1620
0*
1%
1-
0#
#1650
1*
0%
0-
1#
#1680
0*
1%
1-
0#
#1710
1*
0%
0-
1#
#1740
0*
1%
1-
0#
#1770
1*
0%
0-
1#
#1800
0*
1%
1-
0#
#1830
1*
0%
0-
1#
#1860
0*
1%
1-
0#
#1890
1*
0%
0-
1#
#1920
0*
1%
1-
0#
#1950
1*
0%
0-
1#
#1980
0*
1%
1-
0#
#2010
1*
0%
0-
1#
#2040
0*
1%
1-
0#
#2070
1*
0%
0-
1#
#2100
0*
1%
1-
0#
#2130
1*
0%
0-
1#
#2160
0*
1%
1-
0#
#2190
1*
0%
0-
1#
#2220
0*
1%
1-
0#
#2250
1*
0%
0-
1#
#2280
0*
1%
1-
0#
#2310
1*
0%
0-
1#
#2340
0*
1%
1-
0#
#2370
1*
0%
0-
1#
#2400
0*
1%
1-
0#
#2430
1*
0%
0-
1#
#2460
0*
1%
1-
0#
#2490
1*
0%
0-
1#
#2520
0*
1%
1-
0#
#2550
1*
0%
0-
1#
#2580
0*
1%
1-
0#
#2610
1*
0%
0-
1#
#2640
0*
1%
1-
0#
#2670
1*
0%
0-
1#
#2700
0*
1%
1-
0#
#2730
1*
0%
0-
1#
#2760
0*
1%
1-
0#
#2790
1*
0%
0-
1#
#2820
0*
1%
1-
0#
#2850
1*
0%
0-
1#
#2880
0*
1%
1-
0#
#2910
1*
0%
0-
1#
#2940
0*
1%
1-
0#
#2970
1*
0%
0-
1#
#3000
0*
1%
1-
0#
#3030
1*
0%
0-
1#
#3060
0*
1%
1-
0#
#3090
1*
0%
0-
1#
#3120
0*
1%
1-
0#
#3150
1*
0%
0-
1#
#3180
0*
1%
1-
0#
#3210
1*
0%
0-
1#
#3240
0*
1%
1-
0#
#3270
1*
0%
0-
1#
#3300
0*
1%
1-
0#
#3330
1*
0%
0-
1#
#3360
0*
1%
1-
0#
#3390
1*
0%
0-
1#
#3420
0*
1%
1-
0#
#3450
1*
0%
0-
1#
#3480
0*
1%
1-
0#
#3510
1*
0%
0-
1#
#3540
0*
1%
1-
0#
#3570
1*
0%
0-
1#
#3600
0*
1%
1-
0#
#3630
1*
0%
0-
1#
#3660
0*
1%
1-
0#
#3690
1*
0%
0-
1#
#3720
0*
1%
1-
0#
#3750
1*
0%
0-
1#
#3780
0*
1%
1-
0#
#3810
1*
0%
0-
1#
#3840
0*
1%
1-
0#
#3870
1*
0%
0-
1#
#3900
0*
1%
1-
0#
#3930
1*
0%
0-
1#
#3960
0*
1%
1-
0#
#3990
1*
0%
0-
1#
#4020
0*
1%
1-
0#
#4050
1*
0%
0-
1#
#4080
0*
1%
1-
0#
#4110
1*
0%
0-
1#
#4140
0*
1%
1-
0#
#4170
1*
0%
0-
1#
#4200
0*
1%
1-
0#
#4230
1*
0%
0-
1#
#4260
0*
1%
1-
0#
#4290
1*
0%
0-
1#
#4320
0*
1%
1-
0#
#4350
1*
0%
0-
1#
#4380
0*
1%
1-
0#
#4410
1*
0%
0-
1#
#4440
0*
1%
1-
0#
#4470
1*
0%
0-
1#
#4500
0*
1%
1-
0#
#4530
1*
0%
0-
1#
#4560
0*
1%
1-
0#
#4590
1*
0%
0-
1#
#4620
0*
1%
1-
0#
#4650
1*
0%
0-
1#
#4680
0*
1%
1-
0#
#4710
1*
0%
0-
1#
#4740
0*
1%
1-
0#
#4770
1*
0%
0-
1#
#4800
0*
1%
1-
0#
#4830
1*
0%
0-
1#
#4860
0*
1%
1-
0#
#4890
1*
0%
0-
1#
#4920
0*
1%
1-
0#
#4950
1*
0%
0-
1#
#4980
0*
1%
1-
0#
#5010
1*
0%
0-
1#
#5040
0*
1%
1-
0#
#5070
1*
0%
0-
1#
#5100
0*
1%
1-
0#
#5130
1*
0%
0-
1#
#5160
0*
1%
1-
0#
#5190
1*
0%
0-
1#
#5220
0*
1%
1-
0#
#5250
1*
0%
0-
1#
#5280
0*
1%
1-
0#
#5310
1*
0%
0-
1#
#5340
0*
1%
1-
0#
#5370
1*
0%
0-
1#
#5400
0*
1%
1-
0#
#5430
1*
0%
0-
1#
#5460
0*
1%
1-
0#
#5490
1*
0%
0-
1#
#5520
0*
1%
1-
0#
#5550
1*
0%
0-
1#
#5580
0*
1%
1-
0#
#5610
1*
0%
0-
1#
#5640
0*
1%
1-
0#
#5670
1*
0%
0-
1#
#5700
0*
1%
1-
0#
#5730
1*
0%
0-
1#
#5760
0*
1%
1-
0#
#5790
1*
0%
0-
1#
#5820
0*
1%
1-
0#
#5850
1*
0%
0-
1#
#5880
0*
1%
1-
0#
#5910
1*
0%
0-
1#
#5940
0*
1%
1-
0#
#5970
1*
0%
0-
1#
#6000
0*
1%
1-
0#
#6030
1*
0%
0-
1#
#6060
0*
1%
1-
0#
#6090
1*
0%
0-
1#
#6120
0*
1%
1-
0#
#6150
1*
0%
0-
1#
#6180
0*
1%
1-
0#
#6210
1*
0%
0-
1#
#6240
0*
1%
1-
0#
#6270
1*
0%
0-
1#
#6300
0*
1%
1-
0#
#6330
1*
0%
0-
1#
#6360
0*
1%
1-
0#
#6390
1*
0%
0-
1#
#6420
0*
1%
1-
0#
#6450
1*
0%
0-
1#
#6480
0*
1%
1-
0#
#6510
1*
0%
0-
1#
#6540
0*
1%
1-
0#
#6570
1*
0%
0-
1#
#6600
0*
1%
1-
0#
#6630
1*
0%
0-
1#
#6660
0*
1%
1-
0#
#6690
1*
0%
0-
1#
#6720
0*
1%
1-
0#
#6750
1*
0%
0-
1#
#6780
0*
1%
1-
0#
#6810
1*
0%
0-
1#
#6840
0*
1%
1-
0#
#6870
1*
0%
0-
1#
#6900
0*
1%
1-
0#
#6930
1*
0%
0-
1#
#6960
0*
1%
1-
0#
#6990
1*
0%
0-
1#
#7020
0*
1%
1-
0#
#7050
1*
0%
0-
1#
#7080
0*
1%
1-
0#
#7110
1*
0%
0-
1#
#7140
0*
1%
1-
0#
#7170
1*
0%
0-
1#
#7200
0*
1%
1-
0#
#7230
1*
0%
0-
1#
#7260
0*
1%
1-
0#
#7290
1*
0%
0-
1#
#7320
0*
1%
1-
0#
#7350
1*
0%
0-
1#
#7380
0*
1%
1-
0#
#7410
1*
0%
0-
1#
#7440
0*
1%
1-
0#
#7470
1*
0%
0-
1#
#7500
0*
1%
1-
0#
#7530
1*
0%
0-
1#
#7560
0*
1%
1-
0#
#7590
1*
0%
0-
1#
#7620
0*
1%
1-
0#
#7650
1*
0%
0-
1#
#7680
0*
1%
1-
0#
#7710
1*
0%
0-
1#
#7740
0*
1%
1-
0#
#7770
1*
0%
0-
1#
#7800
0*
1%
1-
0#
#7830
1*
0%
0-
1#
#7860
0*
1%
1-
0#
#7890
1*
0%
0-
1#
#7920
0*
1%
1-
0#
#7950
1*
0%
0-
1#
#7980
0*
1%
1-
0#
#8010
1*
0%
0-
1#
#8040
0*
1%
1-
0#
#8070
1*
0%
0-
1#
#8100
0*
1%
1-
0#
#8130
1*
0%
0-
1#
#8160
0*
1%
1-
0#
#8190
1*
0%
0-
1#
#8220
0*
1%
1-
0#
#8250
1*
0%
0-
1#
#8280
0*
1%
1-
0#
#8310
1*
0%
0-
1#
#8340
0*
1%
1-
0#
#8370
1*
0%
0-
1#
#8400
0*
1%
1-
0#
#8430
1*
0%
0-
1#
#8460
0*
1%
1-
0#
#8490
1*
0%
0-
1#
#8520
0*
1%
1-
0#
#8550
1*
0%
0-
1#
#8580
0*
1%
1-
0#
#8610
1*
0%
0-
1#
#8640
0*
1%
1-
0#
#8670
1*
0%
0-
1#
#8700
0*
1%
1-
0#
#8730
1*
0%
0-
1#
#8760
0*
1%
1-
0#
#8790
1*
0%
0-
1#
#8820
0*
1%
1-
0#
#8850
1*
0%
0-
1#
#8880
0*
1%
1-
0#
#8910
1*
0%
0-
1#
#8940
0*
1%
1-
0#
#8970
1*
0%
0-
1#
#9000
0*
1%
1-
0#
#9030
1*
0%
0-
1#
#9060
0*
1%
1-
0#
#9090
1*
0%
0-
1#
#9120
0*
1%
1-
0#
#9150
1*
0%
0-
1#
#9180
0*
1%
1-
0#
#9210
1*
0%
0-
1#
#9240
0*
1%
1-
0#
#9270
1*
0%
0-
1#
#9300
0*
1%
1-
0#
#9330
1*
0%
0-
1#
#9360
0*
1%
1-
0#
#9390
1*
0%
0-
1#
#9420
0*
1%
1-
0#
#9450
1*
0%
0-
1#
#9480
0*
1%
1-
0#
#9510
1*
0%
0-
1#
#9540
0*
1%
1-
0#
#9570
1*
0%
0-
1#
#9600
0*
1%
1-
0#
#9630
1*
0%
0-
1#
#9660
0*
1%
1-
0#
#9690
1*
0%
0-
1#
#9720
0*
1%
1-
0#
#9750
1*
0%
0-
1#
#9780
0*
1%
1-
0#
#9810
1*
0%
0-
1#
#9840
0*
1%
1-
0#
#9870
1*
0%
0-
1#
#9900
0*
1%
1-
0#
#9930
1*
0%
0-
1#
#9960
0*
1%
1-
0#
#9990
1*
0%
0-
1#
