DEC/DEC2T4E/DEC2T4E.v
`ifndef DEC2T4E_V
`define DEC2T4_V

module DEC2T4E(I0,I1,En,Y0,Y1,Y2,Y3);
    input I0,I1,En;
    output Y0,Y1,Y2,Y3;

    not i0(I0_n,I0);
    not i1(I1_n,I1);
    
    nor i2(YY0,I0,I1);
    and i3(Y0,YY0,En);

    nor i4(YY1,I0,I1_n);
    and i5(Y1,YY1,En);

    nor i6(YY2,I0_n,I1);
    and i7(Y2,YY2,En);

    nor i8(YY3,I0_n,I1_n);
    and i9(Y3,YY3,En);
endmodule

`endif

DEC/DEC2T4E/DEC2T4_tb.v
`timescale 1ns/1ns
`include "DEC2T4E.v"

module tb_DEC2T4E();
    integer j;
    reg[0:0] I0,I1,En;
    wire[0:0] Y1,Y2,Y3,Y0;
    initial begin
      for(j=0;j<32;j=j+1) begin
        if(j!=0) #100;
        I0=(j%2==0)?1'b1:1'b0;
        I1=(j%3==0)?1'b0:1'b1;
        En=(j%5==0)?1'b0:1'b1;
      end
    end

    DEC2T4E data(
        .I0(I0),
        .I1(I1),
        .En(En),
        .Y0(Y0),
        .Y1(Y1),
        .Y2(Y2),
        .Y3(Y3)
    );

    initial begin
      $dumpfile("DEC2T4E.vcd");
      $dumpvars(0,tb_DEC2T4E);
      #10000 $finish;
    end
endmodule

DEC/DEC2T4E/DEC2T4E.vcd
$date
	Mon Oct  9 15:48:15 2023
$end
$version
	Icarus Verilog
$end
$timescale
	1ns
$end
$scope module tb_DEC2T4E $end
$var wire 1 ! Y3 $end
$var wire 1 " Y2 $end
$var wire 1 # Y1 $end
$var wire 1 $ Y0 $end
$var reg 1 % En $end
$var reg 1 & I0 $end
$var reg 1 ' I1 $end
$var integer 32 ( j [31:0] $end
$scope module data $end
$var wire 1 % En $end
$var wire 1 & I0 $end
$var wire 1 ) I0_n $end
$var wire 1 ' I1 $end
$var wire 1 * I1_n $end
$var wire 1 $ Y0 $end
$var wire 1 # Y1 $end
$var wire 1 " Y2 $end
$var wire 1 ! Y3 $end
$var wire 1 + YY0 $end
$var wire 1 , YY1 $end
$var wire 1 - YY2 $end
$var wire 1 . YY3 $end
$upscope $end
$upscope $end
$enddefinitions $end
#0
$dumpvars
0.
1-
0,
0+
1*
0)
b1 (
0'
1&
0%
0$
0#
0"
0!
$end
#100
1#
1,
0*
0-
1)
b10 (
1%
1'
0&
#200
1!
1.
0#
0)
0,
b11 (
1&
#300
0!
0.
1$
0#
1*
1)
1+
0,
b100 (
0'
0&
#400
1!
1.
0$
0*
0)
0+
b101 (
1'
1&
#500
0.
0!
1)
1,
b110 (
0%
0&
#600
1"
1*
1-
0)
0,
b111 (
1%
0'
1&
#700
1#
1,
0"
0*
0-
1)
b1000 (
1'
0&
#800
1!
1.
0#
0)
0,
b1001 (
1&
#900
0!
0.
1$
0#
1*
1)
1+
0,
b1010 (
0'
0&
#1000
1.
0$
0*
0)
0+
b1011 (
0%
1'
1&
#1100
0.
1#
0!
1)
1,
b1100 (
1%
0&
#1200
1"
0#
1*
1-
0)
0,
b1101 (
0'
1&
#1300
1#
1,
0"
0*
0-
1)
b1110 (
1'
0&
#1400
1!
1.
0#
0)
0,
b1111 (
1&
#1500
0.
0!
1*
1)
1+
0,
b10000 (
0%
0'
0&
#1600
1!
1.
0*
0)
0+
b10001 (
1%
1'
1&
#1700
0!
0.
1#
1)
1,
b10010 (
0&
#1800
1"
0#
1*
1-
0)
0,
b10011 (
0'
1&
#1900
1#
1,
0"
0*
0-
1)
b10100 (
1'
0&
#2000
1.
0#
0)
0,
b10101 (
0%
1&
#2100
0.
1$
0#
0!
1*
1)
1+
0,
b10110 (
1%
0'
0&
#2200
1!
1.
0$
0*
0)
0+
b10111 (
1'
1&
#2300
0!
0.
1#
1)
1,
b11000 (
0&
#2400
1"
0#
1*
1-
0)
0,
b11001 (
0'
1&
#2500
1,
0"
0*
0-
1)
b11010 (
0%
1'
0&
#2600
1!
1.
0)
0,
b11011 (
1%
1&
#2700
0!
0.
1$
0#
1*
1)
1+
0,
b11100 (
0'
0&
#2800
1!
1.
0$
0*
0)
0+
b11101 (
1'
1&
#2900
0!
0.
1#
1)
1,
b11110 (
0&
#3000
0#
1*
1-
0)
0,
b11111 (
0%
0'
1&
#3100
1#
1,
0*
0-
1)
b100000 (
1%
1'
0&
