CPU/CLA_4.v
`ifndef CLA_4_V
`define CLA_4_V

module CLA_4(
    input[3:0] X,
    input[3:0] Y,
    input[0:0] Cin,
    output[3:0] S,
    output[0:0] Cout
);

    wire[3:0] P=X|Y;
    wire[3:0] G=X&Y;
    wire[3:0] Gn=~G;

    and i1(P0Gn0,P[0],Gn[0]);
    xor(S[0],P0Gn0,Cin);
    nand(P0Cin0,P[0],Cin);
    nand(Cout0,Gn[0],P0Cin0);

    and(P1Gn1,P[1],Gn[1]);
    xor(S[1],P1Gn1,Cout0);
    nand(P1P0Cin0,P[1],P[0],Cin);
    nand(P1G0,P[1],G[0]);
    nand(Cout1,Gn[1],P1G0,P1P0Cin0);

    and(P2Gn2,P[2],Gn[2]);
    xor(S[2],P2Gn2,Cout1);
    nand(P2P1P0Cin0,P[2],P[1],P[0],Cin);
    nand(P2P1G0,P[2],P[1],G[0]);
    nand(P2G1,P[2],G[1]);
    nand(Cout2,Gn[2],P2G1,P2P1G0,P2P1P0Cin0);

    and(P3Gn3,P[3],Gn[3]);
    xor(S[3],P3Gn3,Cout2);
    nand(P3P2P1P0Cin0,P[3],P[2],P[1],P[0],Cin);
    nand(P3P2P1G0,P[3],P[2],P[1],G[0]);
    nand(P3P2G1,P[3],P[2],G[1]);
    nand(P3G2,P[3],G[2]);
    nand(Cout,Gn[3],P3G2,P3P2G1,P3P2P1G0,P3P2P1P0Cin0);

endmodule

`endif

CLA/CLA_16/CLA_16.v
`ifndef CLA_16_V
`define CLA_16_V

`include "CLA/CLA_4/CLA_4.v"
module CLA_16 (
    input [15:0]X,
    input [15:0]Y,
    input Cin,
    output [15:0] S,
    output Cout
);
    wire Cout0, Cout1, Cout2;
    CLA_4 add0 (X[3:0], Y[3:0], Cin, S[3:0], Cout0);
    CLA_4 add1 (X[7:4], Y[7:4], Cout0, S[7:4], Cout1);
    CLA_4 add2 (X[11:8], Y[11:8], Cout1, S[11:8], Cout2);
    CLA_4 add3 (X[15:12], Y[15:12], Cout2, S[15:12], Cout);
endmodule

`endif

CLA/CLA_16/CLA_16_tb.v
`timescale 1ns/1ns
`include "CLA_16.v"
module tb_CLA_16();
    reg[15:0] X,Y;
    reg Cin=0;
    integer j;
    initial begin
        for(j=0;j<1000;j++)begin
            X=j;
            Y=16'hDDDD-j;
            #100;
        end
    end

    CLA_16 data(
        .X(X),
        .Y(Y),
        .Cin(Cin)
    );
    initial begin
        $dumpfile("CLA_16.vcd");
        $dumpvars(0,tb_CLA_16);
        #10000 $finish;
    end
endmodule

CLA/CLA_16/CLA_16.vcd
$date
	Tue Oct 31 08:18:30 2023
$end
$version
	Icarus Verilog
$end
$timescale
	1ns
$end
$scope module tb_CLA_16 $end
$var reg 1 ! Cin $end
$var reg 16 " X [15:0] $end
$var reg 16 # Y [15:0] $end
$var integer 32 $ j [31:0] $end
$scope module data $end
$var wire 1 ! Cin $end
$var wire 16 % X [15:0] $end
$var wire 16 & Y [15:0] $end
$var wire 16 ' S [15:0] $end
$var wire 1 ( Cout2 $end
$var wire 1 ) Cout1 $end
$var wire 1 * Cout0 $end
$var wire 1 + Cout $end
$scope module add0 $end
$var wire 1 ! Cin $end
$var wire 1 * Cout $end
$var wire 1 , Cout0 $end
$var wire 1 - Cout1 $end
$var wire 1 . Cout2 $end
$var wire 4 / G [3:0] $end
$var wire 4 0 Gn [3:0] $end
$var wire 4 1 P [3:0] $end
$var wire 1 2 P0Cin0 $end
$var wire 1 3 P0Gn0 $end
$var wire 1 4 P1G0 $end
$var wire 1 5 P1Gn1 $end
$var wire 1 6 P1P0Cin0 $end
$var wire 1 7 P2G1 $end
$var wire 1 8 P2Gn2 $end
$var wire 1 9 P2P1G0 $end
$var wire 1 : P2P1P0Cin0 $end
$var wire 1 ; P3G2 $end
$var wire 1 < P3Gn3 $end
$var wire 1 = P3P2G1 $end
$var wire 1 > P3P2P1G0 $end
$var wire 1 ? P3P2P1P0Cin0 $end
$var wire 4 @ X [3:0] $end
$var wire 4 A Y [3:0] $end
$var wire 4 B S [3:0] $end
$upscope $end
$scope module add1 $end
$var wire 1 * Cin $end
$var wire 1 ) Cout $end
$var wire 1 C Cout0 $end
$var wire 1 D Cout1 $end
$var wire 1 E Cout2 $end
$var wire 4 F G [3:0] $end
$var wire 4 G Gn [3:0] $end
$var wire 4 H P [3:0] $end
$var wire 1 I P0Cin0 $end
$var wire 1 J P0Gn0 $end
$var wire 1 K P1G0 $end
$var wire 1 L P1Gn1 $end
$var wire 1 M P1P0Cin0 $end
$var wire 1 N P2G1 $end
$var wire 1 O P2Gn2 $end
$var wire 1 P P2P1G0 $end
$var wire 1 Q P2P1P0Cin0 $end
$var wire 1 R P3G2 $end
$var wire 1 S P3Gn3 $end
$var wire 1 T P3P2G1 $end
$var wire 1 U P3P2P1G0 $end
$var wire 1 V P3P2P1P0Cin0 $end
$var wire 4 W X [3:0] $end
$var wire 4 X Y [3:0] $end
$var wire 4 Y S [3:0] $end
$upscope $end
$scope module add2 $end
$var wire 1 ) Cin $end
$var wire 1 ( Cout $end
$var wire 1 Z Cout0 $end
$var wire 1 [ Cout1 $end
$var wire 1 \ Cout2 $end
$var wire 4 ] G [3:0] $end
$var wire 4 ^ Gn [3:0] $end
$var wire 4 _ P [3:0] $end
$var wire 1 ` P0Cin0 $end
$var wire 1 a P0Gn0 $end
$var wire 1 b P1G0 $end
$var wire 1 c P1Gn1 $end
$var wire 1 d P1P0Cin0 $end
$var wire 1 e P2G1 $end
$var wire 1 f P2Gn2 $end
$var wire 1 g P2P1G0 $end
$var wire 1 h P2P1P0Cin0 $end
$var wire 1 i P3G2 $end
$var wire 1 j P3Gn3 $end
$var wire 1 k P3P2G1 $end
$var wire 1 l P3P2P1G0 $end
$var wire 1 m P3P2P1P0Cin0 $end
$var wire 4 n X [3:0] $end
$var wire 4 o Y [3:0] $end
$var wire 4 p S [3:0] $end
$upscope $end
$scope module add3 $end
$var wire 1 ( Cin $end
$var wire 1 + Cout $end
$var wire 1 q Cout0 $end
$var wire 1 r Cout1 $end
$var wire 1 s Cout2 $end
$var wire 4 t G [3:0] $end
$var wire 4 u Gn [3:0] $end
$var wire 4 v P [3:0] $end
$var wire 1 w P0Cin0 $end
$var wire 1 x P0Gn0 $end
$var wire 1 y P1G0 $end
$var wire 1 z P1Gn1 $end
$var wire 1 { P1P0Cin0 $end
$var wire 1 | P2G1 $end
$var wire 1 } P2Gn2 $end
$var wire 1 ~ P2P1G0 $end
$var wire 1 !" P2P1P0Cin0 $end
$var wire 1 "" P3G2 $end
$var wire 1 #" P3Gn3 $end
$var wire 1 $" P3P2G1 $end
$var wire 1 %" P3P2P1G0 $end
$var wire 1 &" P3P2P1P0Cin0 $end
$var wire 4 '" X [3:0] $end
$var wire 4 (" Y [3:0] $end
$var wire 4 )" S [3:0] $end
$upscope $end
$upscope $end
$upscope $end
$enddefinitions $end
#0
$dumpvars
b1101 )"
b1101 ("
b0 '"
1&"
1%"
1$"
1#"
1""
1!"
1~
1}
1|
1{
0z
1y
1x
1w
b1101 v
b1111 u
b0 t
0s
0r
0q
b1101 p
b1101 o
b0 n
1m
1l
1k
1j
1i
1h
1g
1f
1e
1d
0c
1b
1a
1`
b1101 _
b1111 ^
b0 ]
0\
0[
0Z
b1101 Y
b1101 X
b0 W
1V
1U
1T
1S
1R
1Q
1P
1O
1N
1M
0L
1K
1J
1I
b1101 H
b1111 G
b0 F
0E
0D
0C
b1101 B
b1101 A
b0 @
1?
1>
1=
1<
1;
1:
19
18
17
16
05
14
13
12
b1101 1
b1111 0
b0 /
0.
0-
0,
0+
0*
0)
0(
b1101110111011101 '
b1101110111011101 &
b0 %
b0 $
b1101110111011101 #
b0 "
0!
$end
#100
b1100 A
b1 @
b1101110111011100 #
b1101110111011100 &
b1 "
b1 %
b1 $
#200
1-
08
b1101 0
b1011 1
b10 /
b1011 A
b10 @
b1101110111011011 #
b1101110111011011 &
b10 "
b10 %
b10 $
#300
b1010 A
b11 @
b1101110111011010 #
b1101110111011010 &
b11 "
b11 %
b11 $
#400
0-
18
b1111 0
b1101 1
b0 /
b1001 A
b100 @
b1101110111011001 #
b1101110111011001 &
b100 "
b100 %
b100 $
#500
b1000 A
b101 @
b1101110111011000 #
b1101110111011000 &
b101 "
b101 %
b101 $
#600
1-
08
1.
0<
07
b1001 0
b111 1
b110 /
b111 A
b110 @
b1101110111010111 #
b1101110111010111 &
b110 "
b110 %
b110 $
#700
b110 A
b111 @
b1101110111010110 #
b1101110111010110 &
b111 "
b111 %
b111 $
#800
0-
18
0.
1<
17
b1111 0
b1101 1
b0 /
b101 A
b1000 @
b1101110111010101 #
b1101110111010101 &
b1000 "
b1000 %
b1000 $
#900
b100 A
b1001 @
b1101110111010100 #
b1101110111010100 &
b1001 "
b1001 %
b1001 $
#1000
1-
08
b1101 0
b1011 1
b10 /
b11 A
b1010 @
b1101110111010011 #
b1101110111010011 &
b1010 "
b1010 %
b1010 $
#1100
b10 A
b1011 @
b1101110111010010 #
b1101110111010010 &
b1011 "
b1011 %
b1011 $
#1200
0-
18
b1111 0
b1101 1
b0 /
b1 A
b1100 @
b1101110111010001 #
b1101110111010001 &
b1100 "
b1100 %
b1100 $
#1300
b0 A
b1101 @
b1101110111010000 #
b1101110111010000 &
b1101 "
b1101 %
b1101 $
#1400
1*
b1101110111011101 '
b1101 Y
1-
08
0<
1.
0J
07
0=
0;
b1 0
b1100 H
b1111 1
b1110 /
b1111 A
b1100 X
b1110 @
b1101110111001111 #
b1101110111001111 &
b1110 "
b1110 %
b1110 $
#1500
b1110 A
b1111 @
b1101110111001110 #
b1101110111001110 &
b1111 "
b1111 %
b1111 $
#1600
0*
0-
18
1<
0.
b1101110111011101 '
b1101 Y
0C
17
1=
1;
1J
1I
b1111 0
b1101 1
b0 /
b1101 H
b1101 A
b0 @
b1 W
b1101110111001101 #
b1101110111001101 &
b10000 "
b10000 %
b10000 $
#1700
b1100 A
b1 @
b1101110111001100 #
b1101110111001100 &
b10001 "
b10001 %
b10001 $
#1800
1-
08
b1101 0
b1011 1
b10 /
b1011 A
b10 @
b1101110111001011 #
b1101110111001011 &
b10010 "
b10010 %
b10010 $
#1900
b1010 A
b11 @
b1101110111001010 #
b1101110111001010 &
b10011 "
b10011 %
b10011 $
#2000
0-
18
b1111 0
b1101 1
b0 /
b1001 A
b100 @
b1101110111001001 #
b1101110111001001 &
b10100 "
b10100 %
b10100 $
#2100
b1000 A
b101 @
b1101110111001000 #
b1101110111001000 &
b10101 "
b10101 %
b10101 $
#2200
1-
08
1.
0<
07
b1001 0
b111 1
b110 /
b111 A
b110 @
b1101110111000111 #
b1101110111000111 &
b10110 "
b10110 %
b10110 $
#2300
b110 A
b111 @
b1101110111000110 #
b1101110111000110 &
b10111 "
b10111 %
b10111 $
#2400
0-
18
0.
1<
17
b1111 0
b1101 1
b0 /
b101 A
b1000 @
b1101110111000101 #
b1101110111000101 &
b11000 "
b11000 %
b11000 $
#2500
b100 A
b1001 @
b1101110111000100 #
b1101110111000100 &
b11001 "
b11001 %
b11001 $
#2600
1-
08
b1101 0
b1011 1
b10 /
b11 A
b1010 @
b1101110111000011 #
b1101110111000011 &
b11010 "
b11010 %
b11010 $
#2700
b10 A
b1011 @
b1101110111000010 #
b1101110111000010 &
b11011 "
b11011 %
b11011 $
#2800
0-
18
b1111 0
b1101 1
b0 /
b1 A
b1100 @
b1101110111000001 #
b1101110111000001 &
b11100 "
b11100 %
b11100 $
#2900
b0 A
b1101 @
b1101110111000000 #
b1101110111000000 &
b11101 "
b11101 %
b11101 $
#3000
0I
0M
1*
0J
1C
1D
1-
08
0<
1.
1L
0O
0K
07
0=
0;
b1110 G
b1 0
b1011 H
b1 F
b1111 1
b1110 /
b1111 A
b1011 X
b1110 @
b1101110110111111 #
b1101110110111111 &
b11110 "
b11110 %
b11110 $
#3100
b1110 A
b1111 @
b1101110110111110 #
b1101110110111110 &
b11111 "
b11111 %
b11111 $
#3200
0C
1I
1M
0*
b1101110111011101 '
b1101 Y
0-
18
1<
0.
1J
0L
17
1=
1;
1K
b1111 0
b1101 G
b1101 1
b0 /
b10 F
b1101 A
b0 @
b10 W
b1101110110111101 #
b1101110110111101 &
b100000 "
b100000 %
b100000 $
#3300
b1100 A
b1 @
b1101110110111100 #
b1101110110111100 &
b100001 "
b100001 %
b100001 $
#3400
1-
08
b1101 0
b1011 1
b10 /
b1011 A
b10 @
b1101110110111011 #
b1101110110111011 &
b100010 "
b100010 %
b100010 $
#3500
b1010 A
b11 @
b1101110110111010 #
b1101110110111010 &
b100011 "
b100011 %
b100011 $
#3600
0-
18
b1111 0
b1101 1
b0 /
b1001 A
b100 @
b1101110110111001 #
b1101110110111001 &
b100100 "
b100100 %
b100100 $
#3700
b1000 A
b101 @
b1101110110111000 #
b1101110110111000 &
b100101 "
b100101 %
b100101 $
#3800
1-
08
1.
0<
07
b1001 0
b111 1
b110 /
b111 A
b110 @
b1101110110110111 #
b1101110110110111 &
b100110 "
b100110 %
b100110 $
#3900
b110 A
b111 @
b1101110110110110 #
b1101110110110110 &
b100111 "
b100111 %
b100111 $
#4000
0-
18
0.
1<
17
b1111 0
b1101 1
b0 /
b101 A
b1000 @
b1101110110110101 #
b1101110110110101 &
b101000 "
b101000 %
b101000 $
#4100
b100 A
b1001 @
b1101110110110100 #
b1101110110110100 &
b101001 "
b101001 %
b101001 $
#4200
1-
08
b1101 0
b1011 1
b10 /
b11 A
b1010 @
b1101110110110011 #
b1101110110110011 &
b101010 "
b101010 %
b101010 $
#4300
b10 A
b1011 @
b1101110110110010 #
b1101110110110010 &
b101011 "
b101011 %
b101011 $
#4400
0-
18
b1111 0
b1101 1
b0 /
b1 A
b1100 @
b1101110110110001 #
b1101110110110001 &
b101100 "
b101100 %
b101100 $
#4500
b0 A
b1101 @
b1101110110110000 #
b1101110110110000 &
b101101 "
b101101 %
b101101 $
#4600
1*
b1101110111011101 '
b1101 Y
1-
08
0<
1.
0J
07
0=
0;
b1 0
b1010 H
b1111 1
b1110 /
b1111 A
b1010 X
b1110 @
b1101110110101111 #
b1101110110101111 &
b101110 "
b101110 %
b101110 $
#4700
b1110 A
b1111 @
b1101110110101110 #
b1101110110101110 &
b101111 "
b101111 %
b101111 $
#4800
0*
0-
18
1<
0.
b1101110111011101 '
b1101 Y
0C
17
1=
1;
1J
1I
1M
b1111 0
b1101 1
b0 /
b1011 H
b1101 A
b0 @
b11 W
b1101110110101101 #
b1101110110101101 &
b110000 "
b110000 %
b110000 $
#4900
b1100 A
b1 @
b1101110110101100 #
b1101110110101100 &
b110001 "
b110001 %
b110001 $
#5000
1-
08
b1101 0
b1011 1
b10 /
b1011 A
b10 @
b1101110110101011 #
b1101110110101011 &
b110010 "
b110010 %
b110010 $
#5100
b1010 A
b11 @
b1101110110101010 #
b1101110110101010 &
b110011 "
b110011 %
b110011 $
#5200
0-
18
b1111 0
b1101 1
b0 /
b1001 A
b100 @
b1101110110101001 #
b1101110110101001 &
b110100 "
b110100 %
b110100 $
#5300
b1000 A
b101 @
b1101110110101000 #
b1101110110101000 &
b110101 "
b110101 %
b110101 $
#5400
1-
08
1.
0<
07
b1001 0
b111 1
b110 /
b111 A
b110 @
b1101110110100111 #
b1101110110100111 &
b110110 "
b110110 %
b110110 $
#5500
b110 A
b111 @
b1101110110100110 #
b1101110110100110 &
b110111 "
b110111 %
b110111 $
#5600
0-
18
0.
1<
17
b1111 0
b1101 1
b0 /
b101 A
b1000 @
b1101110110100101 #
b1101110110100101 &
b111000 "
b111000 %
b111000 $
#5700
b100 A
b1001 @
b1101110110100100 #
b1101110110100100 &
b111001 "
b111001 %
b111001 $
#5800
1-
08
b1101 0
b1011 1
b10 /
b11 A
b1010 @
b1101110110100011 #
b1101110110100011 &
b111010 "
b111010 %
b111010 $
#5900
b10 A
b1011 @
b1101110110100010 #
b1101110110100010 &
b111011 "
b111011 %
b111011 $
#6000
0-
18
b1111 0
b1101 1
b0 /
b1 A
b1100 @
b1101110110100001 #
b1101110110100001 &
b111100 "
b111100 %
b111100 $
#6100
b0 A
b1101 @
b1101110110100000 #
b1101110110100000 &
b111101 "
b111101 %
b111101 $
#6200
0I
0M
1*
0J
1C
1L
1-
08
0<
1.
0K
07
0=
0;
b1110 G
b1 0
b1 F
b1111 1
b1110 /
b1111 A
b1001 X
b1110 @
b1101110110011111 #
b1101110110011111 &
b111110 "
b111110 %
b111110 $
#6300
b1110 A
b1111 @
b1101110110011110 #
b1101110110011110 &
b111111 "
b111111 %
b111111 $
#6400
0C
1I
0*
0-
18
1<
0.
b1101110111011101 '
b1101 Y
1J
0D
17
1=
1;
0L
1M
1O
1K
b1111 0
b1111 G
b1101 1
b0 /
b1101 H
b0 F
b1101 A
b0 @
b100 W
b1101110110011101 #
b1101110110011101 &
b1000000 "
b1000000 %
b1000000 $
#6500
b1100 A
b1 @
b1101110110011100 #
b1101110110011100 &
b1000001 "
b1000001 %
b1000001 $
#6600
1-
08
b1101 0
b1011 1
b10 /
b1011 A
b10 @
b1101110110011011 #
b1101110110011011 &
b1000010 "
b1000010 %
b1000010 $
#6700
b1010 A
b11 @
b1101110110011010 #
b1101110110011010 &
b1000011 "
b1000011 %
b1000011 $
#6800
0-
18
b1111 0
b1101 1
b0 /
b1001 A
b100 @
b1101110110011001 #
b1101110110011001 &
b1000100 "
b1000100 %
b1000100 $
#6900
b1000 A
b101 @
b1101110110011000 #
b1101110110011000 &
b1000101 "
b1000101 %
b1000101 $
#7000
1-
08
1.
0<
07
b1001 0
b111 1
b110 /
b111 A
b110 @
b1101110110010111 #
b1101110110010111 &
b1000110 "
b1000110 %
b1000110 $
#7100
b110 A
b111 @
b1101110110010110 #
b1101110110010110 &
b1000111 "
b1000111 %
b1000111 $
#7200
0-
18
0.
1<
17
b1111 0
b1101 1
b0 /
b101 A
b1000 @
b1101110110010101 #
b1101110110010101 &
b1001000 "
b1001000 %
b1001000 $
#7300
b100 A
b1001 @
b1101110110010100 #
b1101110110010100 &
b1001001 "
b1001001 %
b1001001 $
#7400
1-
08
b1101 0
b1011 1
b10 /
b11 A
b1010 @
b1101110110010011 #
b1101110110010011 &
b1001010 "
b1001010 %
b1001010 $
#7500
b10 A
b1011 @
b1101110110010010 #
b1101110110010010 &
b1001011 "
b1001011 %
b1001011 $
#7600
0-
18
b1111 0
b1101 1
b0 /
b1 A
b1100 @
b1101110110010001 #
b1101110110010001 &
b1001100 "
b1001100 %
b1001100 $
#7700
b0 A
b1101 @
b1101110110010000 #
b1101110110010000 &
b1001101 "
b1001101 %
b1001101 $
#7800
1*
b1101110111011101 '
b1101 Y
1-
08
0<
1.
0J
07
0=
0;
b1 0
b1100 H
b1111 1
b1110 /
b1111 A
b1000 X
b1110 @
b1101110110001111 #
b1101110110001111 &
b1001110 "
b1001110 %
b1001110 $
#7900
b1110 A
b1111 @
b1101110110001110 #
b1101110110001110 &
b1001111 "
b1001111 %
b1001111 $
#8000
0*
0-
18
1<
0.
b1101110111011101 '
b1101 Y
0C
17
1=
1;
1J
1I
b1111 0
b1101 1
b0 /
b1101 H
b1101 A
b0 @
b101 W
b1101110110001101 #
b1101110110001101 &
b1010000 "
b1010000 %
b1010000 $
#8100
b1100 A
b1 @
b1101110110001100 #
b1101110110001100 &
b1010001 "
b1010001 %
b1010001 $
#8200
1-
08
b1101 0
b1011 1
b10 /
b1011 A
b10 @
b1101110110001011 #
b1101110110001011 &
b1010010 "
b1010010 %
b1010010 $
#8300
b1010 A
b11 @
b1101110110001010 #
b1101110110001010 &
b1010011 "
b1010011 %
b1010011 $
#8400
0-
18
b1111 0
b1101 1
b0 /
b1001 A
b100 @
b1101110110001001 #
b1101110110001001 &
b1010100 "
b1010100 %
b1010100 $
#8500
b1000 A
b101 @
b1101110110001000 #
b1101110110001000 &
b1010101 "
b1010101 %
b1010101 $
#8600
1-
08
1.
0<
07
b1001 0
b111 1
b110 /
b111 A
b110 @
b1101110110000111 #
b1101110110000111 &
b1010110 "
b1010110 %
b1010110 $
#8700
b110 A
b111 @
b1101110110000110 #
b1101110110000110 &
b1010111 "
b1010111 %
b1010111 $
#8800
0-
18
0.
1<
17
b1111 0
b1101 1
b0 /
b101 A
b1000 @
b1101110110000101 #
b1101110110000101 &
b1011000 "
b1011000 %
b1011000 $
#8900
b100 A
b1001 @
b1101110110000100 #
b1101110110000100 &
b1011001 "
b1011001 %
b1011001 $
#9000
1-
08
b1101 0
b1011 1
b10 /
b11 A
b1010 @
b1101110110000011 #
b1101110110000011 &
b1011010 "
b1011010 %
b1011010 $
#9100
b10 A
b1011 @
b1101110110000010 #
b1101110110000010 &
b1011011 "
b1011011 %
b1011011 $
#9200
0-
18
b1111 0
b1101 1
b0 /
b1 A
b1100 @
b1101110110000001 #
b1101110110000001 &
b1011100 "
b1011100 %
b1011100 $
#9300
b0 A
b1101 @
b1101110110000000 #
b1101110110000000 &
b1011101 "
b1011101 %
b1011101 $
#9400
0I
0M
0Q
1*
0J
1C
0O
1D
1E
1-
08
0<
1.
1L
0S
0K
0P
07
0=
0;
b1010 G
b1 0
b111 H
b101 F
b1111 1
b1110 /
b1111 A
b111 X
b1110 @
b1101110101111111 #
b1101110101111111 &
b1011110 "
b1011110 %
b1011110 $
#9500
b1110 A
b1111 @
b1101110101111110 #
b1101110101111110 &
b1011111 "
b1011111 %
b1011111 $
#9600
0C
1I
1M
1Q
0*
b1101110111011101 '
b1101 Y
0-
18
1<
0.
1J
0L
17
1=
1;
1K
1P
0N
b1111 0
b1001 G
b1101 1
b0 /
b110 F
b1101 A
b0 @
b110 W
b1101110101111101 #
b1101110101111101 &
b1100000 "
b1100000 %
b1100000 $
#9700
b1100 A
b1 @
b1101110101111100 #
b1101110101111100 &
b1100001 "
b1100001 %
b1100001 $
#9800
1-
08
b1101 0
b1011 1
b10 /
b1011 A
b10 @
b1101110101111011 #
b1101110101111011 &
b1100010 "
b1100010 %
b1100010 $
#9900
b1010 A
b11 @
b1101110101111010 #
b1101110101111010 &
b1100011 "
b1100011 %
b1100011 $
#10000
0-
18
b1111 0
b1101 1
b0 /
b1001 A
b100 @
b1101110101111001 #
b1101110101111001 &
b1100100 "
b1100100 %
b1100100 $
