CPT4/CPT4.v
`ifndef CPT4_V
`define CPT4_V
module CPT4(
    input [3:0]A,
    input [3:0]B,
    output Y
);
    xor x0(Y0,A[0],B[0]);
    xor x1(Y1,A[1],B[1]);
    xor x2(Y2,A[2],B[2]);
    xor x3(Y3,A[3],B[3]);
    nor n1(Y,Y0,Y1,Y2,Y3);
endmodule
`endif

CPT4/CPT4_tb.v
`include "CPT4.v"
`timescale 1ns/1ns
module tb_CPT4();
    reg[3:0]A,B;
    wire Y;
    integer j=0;
    initial begin 
        for(j=0;j<1000;j++)begin
            A=(5*j+4)%16;
            B=(3*j)%16;
            #50;
        end
    end

    CPT4 data(
        .A(A),
        .B(B),
        .Y(Y)
    );

    initial begin
      $dumpfile("CPT4.vcd");
      $dumpvars(0,tb_CPT4);
      #10000 $finish;
    end
endmodule

CPT4/CPT4.vcd
$date
	Tue Oct 31 01:12:48 2023
$end
$version
	Icarus Verilog
$end
$timescale
	1ns
$end
$scope module tb_CPT4 $end
$var wire 1 ! Y $end
$var reg 4 " A [3:0] $end
$var reg 4 # B [3:0] $end
$var integer 32 $ j [31:0] $end
$scope module data $end
$var wire 4 % A [3:0] $end
$var wire 4 & B [3:0] $end
$var wire 1 ! Y $end
$var wire 1 ' Y0 $end
$var wire 1 ( Y1 $end
$var wire 1 ) Y2 $end
$var wire 1 * Y3 $end
$upscope $end
$upscope $end
$enddefinitions $end
#0
$dumpvars
0*
1)
0(
0'
b0 &
b100 %
b0 $
b0 #
b100 "
0!
$end
#50
1(
0)
1*
b11 #
b11 &
b1001 "
b1001 %
b1 $
#100
0(
b110 #
b110 &
b1110 "
b1110 %
b10 $
#150
1(
b1001 #
b1001 &
b11 "
b11 %
b11 $
#200
1)
0(
0*
b1100 #
b1100 &
b1000 "
b1000 %
b100 $
#250
1(
0)
b1111 #
b1111 &
b1101 "
b1101 %
b101 $
#300
1!
0(
b10 #
b10 &
b10 "
b10 %
b110 $
#350
0!
1(
b101 #
b101 &
b111 "
b111 %
b111 $
#400
1)
0(
b1000 #
b1000 &
b1100 "
b1100 %
b1000 $
#450
1(
0)
1*
b1011 #
b1011 &
b1 "
b1 %
b1001 $
#500
0(
b1110 #
b1110 &
b110 "
b110 %
b1010 $
#550
1(
b1 #
b1 &
b1011 "
b1011 %
b1011 $
#600
1)
0(
0*
b100 #
b100 &
b0 "
b0 %
b1100 $
#650
1(
0)
b111 #
b111 &
b101 "
b101 %
b1101 $
#700
1!
0(
b1010 #
b1010 &
b1010 "
b1010 %
b1110 $
#750
0!
1(
b1101 #
b1101 &
b1111 "
b1111 %
b1111 $
#800
1)
0(
b0 #
b0 &
b100 "
b100 %
b10000 $
#850
1(
0)
1*
b11 #
b11 &
b1001 "
b1001 %
b10001 $
#900
0(
b110 #
b110 &
b1110 "
b1110 %
b10010 $
#950
1(
b1001 #
b1001 &
b11 "
b11 %
b10011 $
#1000
1)
0(
0*
b1100 #
b1100 &
b1000 "
b1000 %
b10100 $
#1050
1(
0)
b1111 #
b1111 &
b1101 "
b1101 %
b10101 $
#1100
1!
0(
b10 #
b10 &
b10 "
b10 %
b10110 $
#1150
0!
1(
b101 #
b101 &
b111 "
b111 %
b10111 $
#1200
1)
0(
b1000 #
b1000 &
b1100 "
b1100 %
b11000 $
#1250
1(
0)
1*
b1011 #
b1011 &
b1 "
b1 %
b11001 $
#1300
0(
b1110 #
b1110 &
b110 "
b110 %
b11010 $
#1350
1(
b1 #
b1 &
b1011 "
b1011 %
b11011 $
#1400
1)
0(
0*
b100 #
b100 &
b0 "
b0 %
b11100 $
#1450
1(
0)
b111 #
b111 &
b101 "
b101 %
b11101 $
#1500
1!
0(
b1010 #
b1010 &
b1010 "
b1010 %
b11110 $
#1550
0!
1(
b1101 #
b1101 &
b1111 "
b1111 %
b11111 $
#1600
1)
0(
b0 #
b0 &
b100 "
b100 %
b100000 $
#1650
1(
0)
1*
b11 #
b11 &
b1001 "
b1001 %
b100001 $
#1700
0(
b110 #
b110 &
b1110 "
b1110 %
b100010 $
#1750
1(
b1001 #
b1001 &
b11 "
b11 %
b100011 $
#1800
1)
0(
0*
b1100 #
b1100 &
b1000 "
b1000 %
b100100 $
#1850
1(
0)
b1111 #
b1111 &
b1101 "
b1101 %
b100101 $
#1900
1!
0(
b10 #
b10 &
b10 "
b10 %
b100110 $
#1950
0!
1(
b101 #
b101 &
b111 "
b111 %
b100111 $
#2000
1)
0(
b1000 #
b1000 &
b1100 "
b1100 %
b101000 $
#2050
1(
0)
1*
b1011 #
b1011 &
b1 "
b1 %
b101001 $
#2100
0(
b1110 #
b1110 &
b110 "
b110 %
b101010 $
#2150
1(
b1 #
b1 &
b1011 "
b1011 %
b101011 $
#2200
1)
0(
0*
b100 #
b100 &
b0 "
b0 %
b101100 $
#2250
1(
0)
b111 #
b111 &
b101 "
b101 %
b101101 $
#2300
1!
0(
b1010 #
b1010 &
b1010 "
b1010 %
b101110 $
#2350
0!
1(
b1101 #
b1101 &
b1111 "
b1111 %
b101111 $
#2400
1)
0(
b0 #
b0 &
b100 "
b100 %
b110000 $
#2450
1(
0)
1*
b11 #
b11 &
b1001 "
b1001 %
b110001 $
#2500
0(
b110 #
b110 &
b1110 "
b1110 %
b110010 $
#2550
1(
b1001 #
b1001 &
b11 "
b11 %
b110011 $
#2600
1)
0(
0*
b1100 #
b1100 &
b1000 "
b1000 %
b110100 $
#2650
1(
0)
b1111 #
b1111 &
b1101 "
b1101 %
b110101 $
#2700
1!
0(
b10 #
b10 &
b10 "
b10 %
b110110 $
#2750
0!
1(
b101 #
b101 &
b111 "
b111 %
b110111 $
#2800
1)
0(
b1000 #
b1000 &
b1100 "
b1100 %
b111000 $
#2850
1(
0)
1*
b1011 #
b1011 &
b1 "
b1 %
b111001 $
#2900
0(
b1110 #
b1110 &
b110 "
b110 %
b111010 $
#2950
1(
b1 #
b1 &
b1011 "
b1011 %
b111011 $
#3000
1)
0(
0*
b100 #
b100 &
b0 "
b0 %
b111100 $
#3050
1(
0)
b111 #
b111 &
b101 "
b101 %
b111101 $
#3100
1!
0(
b1010 #
b1010 &
b1010 "
b1010 %
b111110 $
#3150
0!
1(
b1101 #
b1101 &
b1111 "
b1111 %
b111111 $
#3200
1)
0(
b0 #
b0 &
b100 "
b100 %
b1000000 $
#3250
1(
0)
1*
b11 #
b11 &
b1001 "
b1001 %
b1000001 $
#3300
0(
b110 #
b110 &
b1110 "
b1110 %
b1000010 $
#3350
1(
b1001 #
b1001 &
b11 "
b11 %
b1000011 $
#3400
1)
0(
0*
b1100 #
b1100 &
b1000 "
b1000 %
b1000100 $
#3450
1(
0)
b1111 #
b1111 &
b1101 "
b1101 %
b1000101 $
#3500
1!
0(
b10 #
b10 &
b10 "
b10 %
b1000110 $
#3550
0!
1(
b101 #
b101 &
b111 "
b111 %
b1000111 $
#3600
1)
0(
b1000 #
b1000 &
b1100 "
b1100 %
b1001000 $
#3650
1(
0)
1*
b1011 #
b1011 &
b1 "
b1 %
b1001001 $
#3700
0(
b1110 #
b1110 &
b110 "
b110 %
b1001010 $
#3750
1(
b1 #
b1 &
b1011 "
b1011 %
b1001011 $
#3800
1)
0(
0*
b100 #
b100 &
b0 "
b0 %
b1001100 $
#3850
1(
0)
b111 #
b111 &
b101 "
b101 %
b1001101 $
#3900
1!
0(
b1010 #
b1010 &
b1010 "
b1010 %
b1001110 $
#3950
0!
1(
b1101 #
b1101 &
b1111 "
b1111 %
b1001111 $
#4000
1)
0(
b0 #
b0 &
b100 "
b100 %
b1010000 $
#4050
1(
0)
1*
b11 #
b11 &
b1001 "
b1001 %
b1010001 $
#4100
0(
b110 #
b110 &
b1110 "
b1110 %
b1010010 $
#4150
1(
b1001 #
b1001 &
b11 "
b11 %
b1010011 $
#4200
1)
0(
0*
b1100 #
b1100 &
b1000 "
b1000 %
b1010100 $
#4250
1(
0)
b1111 #
b1111 &
b1101 "
b1101 %
b1010101 $
#4300
1!
0(
b10 #
b10 &
b10 "
b10 %
b1010110 $
#4350
0!
1(
b101 #
b101 &
b111 "
b111 %
b1010111 $
#4400
1)
0(
b1000 #
b1000 &
b1100 "
b1100 %
b1011000 $
#4450
1(
0)
1*
b1011 #
b1011 &
b1 "
b1 %
b1011001 $
#4500
0(
b1110 #
b1110 &
b110 "
b110 %
b1011010 $
#4550
1(
b1 #
b1 &
b1011 "
b1011 %
b1011011 $
#4600
1)
0(
0*
b100 #
b100 &
b0 "
b0 %
b1011100 $
#4650
1(
0)
b111 #
b111 &
b101 "
b101 %
b1011101 $
#4700
1!
0(
b1010 #
b1010 &
b1010 "
b1010 %
b1011110 $
#4750
0!
1(
b1101 #
b1101 &
b1111 "
b1111 %
b1011111 $
#4800
1)
0(
b0 #
b0 &
b100 "
b100 %
b1100000 $
#4850
1(
0)
1*
b11 #
b11 &
b1001 "
b1001 %
b1100001 $
#4900
0(
b110 #
b110 &
b1110 "
b1110 %
b1100010 $
#4950
1(
b1001 #
b1001 &
b11 "
b11 %
b1100011 $
#5000
1)
0(
0*
b1100 #
b1100 &
b1000 "
b1000 %
b1100100 $
#5050
1(
0)
b1111 #
b1111 &
b1101 "
b1101 %
b1100101 $
#5100
1!
0(
b10 #
b10 &
b10 "
b10 %
b1100110 $
#5150
0!
1(
b101 #
b101 &
b111 "
b111 %
b1100111 $
#5200
1)
0(
b1000 #
b1000 &
b1100 "
b1100 %
b1101000 $
#5250
1(
0)
1*
b1011 #
b1011 &
b1 "
b1 %
b1101001 $
#5300
0(
b1110 #
b1110 &
b110 "
b110 %
b1101010 $
#5350
1(
b1 #
b1 &
b1011 "
b1011 %
b1101011 $
#5400
1)
0(
0*
b100 #
b100 &
b0 "
b0 %
b1101100 $
#5450
1(
0)
b111 #
b111 &
b101 "
b101 %
b1101101 $
#5500
1!
0(
b1010 #
b1010 &
b1010 "
b1010 %
b1101110 $
#5550
0!
1(
b1101 #
b1101 &
b1111 "
b1111 %
b1101111 $
#5600
1)
0(
b0 #
b0 &
b100 "
b100 %
b1110000 $
#5650
1(
0)
1*
b11 #
b11 &
b1001 "
b1001 %
b1110001 $
#5700
0(
b110 #
b110 &
b1110 "
b1110 %
b1110010 $
#5750
1(
b1001 #
b1001 &
b11 "
b11 %
b1110011 $
#5800
1)
0(
0*
b1100 #
b1100 &
b1000 "
b1000 %
b1110100 $
#5850
1(
0)
b1111 #
b1111 &
b1101 "
b1101 %
b1110101 $
#5900
1!
0(
b10 #
b10 &
b10 "
b10 %
b1110110 $
#5950
0!
1(
b101 #
b101 &
b111 "
b111 %
b1110111 $
#6000
1)
0(
b1000 #
b1000 &
b1100 "
b1100 %
b1111000 $
#6050
1(
0)
1*
b1011 #
b1011 &
b1 "
b1 %
b1111001 $
#6100
0(
b1110 #
b1110 &
b110 "
b110 %
b1111010 $
#6150
1(
b1 #
b1 &
b1011 "
b1011 %
b1111011 $
#6200
1)
0(
0*
b100 #
b100 &
b0 "
b0 %
b1111100 $
#6250
1(
0)
b111 #
b111 &
b101 "
b101 %
b1111101 $
#6300
1!
0(
b1010 #
b1010 &
b1010 "
b1010 %
b1111110 $
#6350
0!
1(
b1101 #
b1101 &
b1111 "
b1111 %
b1111111 $
#6400
1)
0(
b0 #
b0 &
b100 "
b100 %
b10000000 $
#6450
1(
0)
1*
b11 #
b11 &
b1001 "
b1001 %
b10000001 $
#6500
0(
b110 #
b110 &
b1110 "
b1110 %
b10000010 $
#6550
1(
b1001 #
b1001 &
b11 "
b11 %
b10000011 $
#6600
1)
0(
0*
b1100 #
b1100 &
b1000 "
b1000 %
b10000100 $
#6650
1(
0)
b1111 #
b1111 &
b1101 "
b1101 %
b10000101 $
#6700
1!
0(
b10 #
b10 &
b10 "
b10 %
b10000110 $
#6750
0!
1(
b101 #
b101 &
b111 "
b111 %
b10000111 $
#6800
1)
0(
b1000 #
b1000 &
b1100 "
b1100 %
b10001000 $
#6850
1(
0)
1*
b1011 #
b1011 &
b1 "
b1 %
b10001001 $
#6900
0(
b1110 #
b1110 &
b110 "
b110 %
b10001010 $
#6950
1(
b1 #
b1 &
b1011 "
b1011 %
b10001011 $
#7000
1)
0(
0*
b100 #
b100 &
b0 "
b0 %
b10001100 $
#7050
1(
0)
b111 #
b111 &
b101 "
b101 %
b10001101 $
#7100
1!
0(
b1010 #
b1010 &
b1010 "
b1010 %
b10001110 $
#7150
0!
1(
b1101 #
b1101 &
b1111 "
b1111 %
b10001111 $
#7200
1)
0(
b0 #
b0 &
b100 "
b100 %
b10010000 $
#7250
1(
0)
1*
b11 #
b11 &
b1001 "
b1001 %
b10010001 $
#7300
0(
b110 #
b110 &
b1110 "
b1110 %
b10010010 $
#7350
1(
b1001 #
b1001 &
b11 "
b11 %
b10010011 $
#7400
1)
0(
0*
b1100 #
b1100 &
b1000 "
b1000 %
b10010100 $
#7450
1(
0)
b1111 #
b1111 &
b1101 "
b1101 %
b10010101 $
#7500
1!
0(
b10 #
b10 &
b10 "
b10 %
b10010110 $
#7550
0!
1(
b101 #
b101 &
b111 "
b111 %
b10010111 $
#7600
1)
0(
b1000 #
b1000 &
b1100 "
b1100 %
b10011000 $
#7650
1(
0)
1*
b1011 #
b1011 &
b1 "
b1 %
b10011001 $
#7700
0(
b1110 #
b1110 &
b110 "
b110 %
b10011010 $
#7750
1(
b1 #
b1 &
b1011 "
b1011 %
b10011011 $
#7800
1)
0(
0*
b100 #
b100 &
b0 "
b0 %
b10011100 $
#7850
1(
0)
b111 #
b111 &
b101 "
b101 %
b10011101 $
#7900
1!
0(
b1010 #
b1010 &
b1010 "
b1010 %
b10011110 $
#7950
0!
1(
b1101 #
b1101 &
b1111 "
b1111 %
b10011111 $
#8000
1)
0(
b0 #
b0 &
b100 "
b100 %
b10100000 $
#8050
1(
0)
1*
b11 #
b11 &
b1001 "
b1001 %
b10100001 $
#8100
0(
b110 #
b110 &
b1110 "
b1110 %
b10100010 $
#8150
1(
b1001 #
b1001 &
b11 "
b11 %
b10100011 $
#8200
1)
0(
0*
b1100 #
b1100 &
b1000 "
b1000 %
b10100100 $
#8250
1(
0)
b1111 #
b1111 &
b1101 "
b1101 %
b10100101 $
#8300
1!
0(
b10 #
b10 &
b10 "
b10 %
b10100110 $
#8350
0!
1(
b101 #
b101 &
b111 "
b111 %
b10100111 $
#8400
1)
0(
b1000 #
b1000 &
b1100 "
b1100 %
b10101000 $
#8450
1(
0)
1*
b1011 #
b1011 &
b1 "
b1 %
b10101001 $
#8500
0(
b1110 #
b1110 &
b110 "
b110 %
b10101010 $
#8550
1(
b1 #
b1 &
b1011 "
b1011 %
b10101011 $
#8600
1)
0(
0*
b100 #
b100 &
b0 "
b0 %
b10101100 $
#8650
1(
0)
b111 #
b111 &
b101 "
b101 %
b10101101 $
#8700
1!
0(
b1010 #
b1010 &
b1010 "
b1010 %
b10101110 $
#8750
0!
1(
b1101 #
b1101 &
b1111 "
b1111 %
b10101111 $
#8800
1)
0(
b0 #
b0 &
b100 "
b100 %
b10110000 $
#8850
1(
0)
1*
b11 #
b11 &
b1001 "
b1001 %
b10110001 $
#8900
0(
b110 #
b110 &
b1110 "
b1110 %
b10110010 $
#8950
1(
b1001 #
b1001 &
b11 "
b11 %
b10110011 $
#9000
1)
0(
0*
b1100 #
b1100 &
b1000 "
b1000 %
b10110100 $
#9050
1(
0)
b1111 #
b1111 &
b1101 "
b1101 %
b10110101 $
#9100
1!
0(
b10 #
b10 &
b10 "
b10 %
b10110110 $
#9150
0!
1(
b101 #
b101 &
b111 "
b111 %
b10110111 $
#9200
1)
0(
b1000 #
b1000 &
b1100 "
b1100 %
b10111000 $
#9250
1(
0)
1*
b1011 #
b1011 &
b1 "
b1 %
b10111001 $
#9300
0(
b1110 #
b1110 &
b110 "
b110 %
b10111010 $
#9350
1(
b1 #
b1 &
b1011 "
b1011 %
b10111011 $
#9400
1)
0(
0*
b100 #
b100 &
b0 "
b0 %
b10111100 $
#9450
1(
0)
b111 #
b111 &
b101 "
b101 %
b10111101 $
#9500
1!
0(
b1010 #
b1010 &
b1010 "
b1010 %
b10111110 $
#9550
0!
1(
b1101 #
b1101 &
b1111 "
b1111 %
b10111111 $
#9600
1)
0(
b0 #
b0 &
b100 "
b100 %
b11000000 $
#9650
1(
0)
1*
b11 #
b11 &
b1001 "
b1001 %
b11000001 $
#9700
0(
b110 #
b110 &
b1110 "
b1110 %
b11000010 $
#9750
1(
b1001 #
b1001 &
b11 "
b11 %
b11000011 $
#9800
1)
0(
0*
b1100 #
b1100 &
b1000 "
b1000 %
b11000100 $
#9850
1(
0)
b1111 #
b1111 &
b1101 "
b1101 %
b11000101 $
#9900
1!
0(
b10 #
b10 &
b10 "
b10 %
b11000110 $
#9950
0!
1(
b101 #
b101 &
b111 "
b111 %
b11000111 $
#10000
1)
0(
b1000 #
b1000 &
b1100 "
b1100 %
b11001000 $
