ENC/ENC8T3/ENC8T3.v
`ifndef ENC8T3_V
`define ENC8T3_V

module ENC8T3(
    input[7:0] I,
    output[2:0] Y,
    output Idle
);
    //not nt1(IN,I);
    not n0(In0,I[0]);
    not n1(In1,I[1]);
    not n2(In2,I[2]);
    not n3(In3,I[3]);
    not n4(In4,I[4]);
    not n5(In5,I[5]);
    not n6(In6,I[6]);
    not n7(In7,I[7]);

    or o1(Y[2],I[4],I[5],I[6],I[7]);

    and a1(S1,I[2],In4,In5);
    and a2(S2,I[3],In4,In5);
    or o2(Y[1],S1,S2,I[6],I[7]);

    and a3(S4,I[1],In2,In4,In6);
    and a4(S5,I[3],In4,In6);
    and a5(S6,I[5],In6);
    or o3(Y[0],S4,S5,S6,I[7]);

    and a6(Idle,In0,In1,In2,In3,In4,In5,In6,In7);

endmodule

`endif

ENC/ENC8T3/ENC8T3_tb.v
`timescale 1ns/1ns
`include "ENC8T3.v"

module tb_ENC8T3();
    reg[7:0] I;
    integer j=0;

    initial begin
        for(j=0;j<512;j=j+1)begin
            I=j;
            #5;
        end
    end
    ENC8T3 data2(
        .I(I)
    );

    initial begin
        $dumpfile("ENC8T3.vcd");
        $dumpvars(0,tb_ENC8T3);
        #10000 $finish;
    end
endmodule

ENC/ENC8T3/ENC8T3.vcd
$date
	Tue Oct 31 08:03:08 2023
$end
$version
	Icarus Verilog
$end
$timescale
	1ns
$end
$scope module tb_ENC8T3 $end
$var reg 8 ! I [7:0] $end
$var integer 32 " j [31:0] $end
$scope module data2 $end
$var wire 8 # I [7:0] $end
$var wire 1 $ Idle $end
$var wire 1 % In0 $end
$var wire 1 & In1 $end
$var wire 1 ' In2 $end
$var wire 1 ( In3 $end
$var wire 1 ) In4 $end
$var wire 1 * In5 $end
$var wire 1 + In6 $end
$var wire 1 , In7 $end
$var wire 1 - S1 $end
$var wire 1 . S2 $end
$var wire 1 / S4 $end
$var wire 1 0 S5 $end
$var wire 1 1 S6 $end
$var wire 3 2 Y [2:0] $end
$upscope $end
$upscope $end
$enddefinitions $end
#0
$dumpvars
b0 2
01
00
0/
0.
0-
1,
1+
1*
1)
1(
1'
1&
1%
1$
b0 #
b0 "
b0 !
$end
#5
0$
0%
b1 !
b1 #
b1 "
#10
b1 2
1%
0&
1/
b10 !
b10 #
b10 "
#15
0%
b11 !
b11 #
b11 "
#20
b10 2
1%
1&
0'
1-
0/
b100 !
b100 #
b100 "
#25
0%
b101 !
b101 #
b101 "
#30
1%
0&
b110 !
b110 #
b110 "
#35
0%
b111 !
b111 #
b111 "
#40
b11 2
1%
1&
1'
0(
0-
1.
10
b1000 !
b1000 #
b1000 "
#45
0%
b1001 !
b1001 #
b1001 "
#50
1%
0&
1/
b1010 !
b1010 #
b1010 "
#55
0%
b1011 !
b1011 #
b1011 "
#60
1%
1&
0'
1-
0/
b1100 !
b1100 #
b1100 "
#65
0%
b1101 !
b1101 #
b1101 "
#70
1%
0&
b1110 !
b1110 #
b1110 "
#75
0%
b1111 !
b1111 #
b1111 "
#80
1%
1&
1'
1(
0)
b100 2
0-
0.
00
b10000 !
b10000 #
b10000 "
#85
0%
b10001 !
b10001 #
b10001 "
#90
1%
0&
b10010 !
b10010 #
b10010 "
#95
0%
b10011 !
b10011 #
b10011 "
#100
1%
1&
0'
b10100 !
b10100 #
b10100 "
#105
0%
b10101 !
b10101 #
b10101 "
#110
1%
0&
b10110 !
b10110 #
b10110 "
#115
0%
b10111 !
b10111 #
b10111 "
#120
1%
1&
1'
0(
b11000 !
b11000 #
b11000 "
#125
0%
b11001 !
b11001 #
b11001 "
#130
1%
0&
b11010 !
b11010 #
b11010 "
#135
0%
b11011 !
b11011 #
b11011 "
#140
1%
1&
0'
b11100 !
b11100 #
b11100 "
#145
0%
b11101 !
b11101 #
b11101 "
#150
1%
0&
b11110 !
b11110 #
b11110 "
#155
0%
b11111 !
b11111 #
b11111 "
#160
b101 2
1%
1&
1'
1(
1)
0*
11
b100000 !
b100000 #
b100000 "
#165
0%
b100001 !
b100001 #
b100001 "
#170
1%
0&
1/
b100010 !
b100010 #
b100010 "
#175
0%
b100011 !
b100011 #
b100011 "
#180
1%
1&
0'
0/
b100100 !
b100100 #
b100100 "
#185
0%
b100101 !
b100101 #
b100101 "
#190
1%
0&
b100110 !
b100110 #
b100110 "
#195
0%
b100111 !
b100111 #
b100111 "
#200
1%
1&
1'
0(
10
b101000 !
b101000 #
b101000 "
#205
0%
b101001 !
b101001 #
b101001 "
#210
1%
0&
1/
b101010 !
b101010 #
b101010 "
#215
0%
b101011 !
b101011 #
b101011 "
#220
1%
1&
0'
0/
b101100 !
b101100 #
b101100 "
#225
0%
b101101 !
b101101 #
b101101 "
#230
1%
0&
b101110 !
b101110 #
b101110 "
#235
0%
b101111 !
b101111 #
b101111 "
#240
1%
1&
1'
1(
0)
00
b110000 !
b110000 #
b110000 "
#245
0%
b110001 !
b110001 #
b110001 "
#250
1%
0&
b110010 !
b110010 #
b110010 "
#255
0%
b110011 !
b110011 #
b110011 "
#260
1%
1&
0'
b110100 !
b110100 #
b110100 "
#265
0%
b110101 !
b110101 #
b110101 "
#270
1%
0&
b110110 !
b110110 #
b110110 "
#275
0%
b110111 !
b110111 #
b110111 "
#280
1%
1&
1'
0(
b111000 !
b111000 #
b111000 "
#285
0%
b111001 !
b111001 #
b111001 "
#290
1%
0&
b111010 !
b111010 #
b111010 "
#295
0%
b111011 !
b111011 #
b111011 "
#300
1%
1&
0'
b111100 !
b111100 #
b111100 "
#305
0%
b111101 !
b111101 #
b111101 "
#310
1%
0&
b111110 !
b111110 #
b111110 "
#315
0%
b111111 !
b111111 #
b111111 "
#320
1%
1&
1'
1(
1)
1*
0+
b110 2
01
b1000000 !
b1000000 #
b1000000 "
#325
0%
b1000001 !
b1000001 #
b1000001 "
#330
1%
0&
b1000010 !
b1000010 #
b1000010 "
#335
0%
b1000011 !
b1000011 #
b1000011 "
#340
1%
1&
0'
1-
b1000100 !
b1000100 #
b1000100 "
#345
0%
b1000101 !
b1000101 #
b1000101 "
#350
1%
0&
b1000110 !
b1000110 #
b1000110 "
#355
0%
b1000111 !
b1000111 #
b1000111 "
#360
1%
1&
1'
0(
0-
1.
b1001000 !
b1001000 #
b1001000 "
#365
0%
b1001001 !
b1001001 #
b1001001 "
#370
1%
0&
b1001010 !
b1001010 #
b1001010 "
#375
0%
b1001011 !
b1001011 #
b1001011 "
#380
1%
1&
0'
1-
b1001100 !
b1001100 #
b1001100 "
#385
0%
b1001101 !
b1001101 #
b1001101 "
#390
1%
0&
b1001110 !
b1001110 #
b1001110 "
#395
0%
b1001111 !
b1001111 #
b1001111 "
#400
1%
1&
1'
1(
0)
0-
0.
b1010000 !
b1010000 #
b1010000 "
#405
0%
b1010001 !
b1010001 #
b1010001 "
#410
1%
0&
b1010010 !
b1010010 #
b1010010 "
#415
0%
b1010011 !
b1010011 #
b1010011 "
#420
1%
1&
0'
b1010100 !
b1010100 #
b1010100 "
#425
0%
b1010101 !
b1010101 #
b1010101 "
#430
1%
0&
b1010110 !
b1010110 #
b1010110 "
#435
0%
b1010111 !
b1010111 #
b1010111 "
#440
1%
1&
1'
0(
b1011000 !
b1011000 #
b1011000 "
#445
0%
b1011001 !
b1011001 #
b1011001 "
#450
1%
0&
b1011010 !
b1011010 #
b1011010 "
#455
0%
b1011011 !
b1011011 #
b1011011 "
#460
1%
1&
0'
b1011100 !
b1011100 #
b1011100 "
#465
0%
b1011101 !
b1011101 #
b1011101 "
#470
1%
0&
b1011110 !
b1011110 #
b1011110 "
#475
0%
b1011111 !
b1011111 #
b1011111 "
#480
1%
1&
1'
1(
1)
0*
b1100000 !
b1100000 #
b1100000 "
#485
0%
b1100001 !
b1100001 #
b1100001 "
#490
1%
0&
b1100010 !
b1100010 #
b1100010 "
#495
0%
b1100011 !
b1100011 #
b1100011 "
#500
1%
1&
0'
b1100100 !
b1100100 #
b1100100 "
#505
0%
b1100101 !
b1100101 #
b1100101 "
#510
1%
0&
b1100110 !
b1100110 #
b1100110 "
#515
0%
b1100111 !
b1100111 #
b1100111 "
#520
1%
1&
1'
0(
b1101000 !
b1101000 #
b1101000 "
#525
0%
b1101001 !
b1101001 #
b1101001 "
#530
1%
0&
b1101010 !
b1101010 #
b1101010 "
#535
0%
b1101011 !
b1101011 #
b1101011 "
#540
1%
1&
0'
b1101100 !
b1101100 #
b1101100 "
#545
0%
b1101101 !
b1101101 #
b1101101 "
#550
1%
0&
b1101110 !
b1101110 #
b1101110 "
#555
0%
b1101111 !
b1101111 #
b1101111 "
#560
1%
1&
1'
1(
0)
b1110000 !
b1110000 #
b1110000 "
#565
0%
b1110001 !
b1110001 #
b1110001 "
#570
1%
0&
b1110010 !
b1110010 #
b1110010 "
#575
0%
b1110011 !
b1110011 #
b1110011 "
#580
1%
1&
0'
b1110100 !
b1110100 #
b1110100 "
#585
0%
b1110101 !
b1110101 #
b1110101 "
#590
1%
0&
b1110110 !
b1110110 #
b1110110 "
#595
0%
b1110111 !
b1110111 #
b1110111 "
#600
1%
1&
1'
0(
b1111000 !
b1111000 #
b1111000 "
#605
0%
b1111001 !
b1111001 #
b1111001 "
#610
1%
0&
b1111010 !
b1111010 #
b1111010 "
#615
0%
b1111011 !
b1111011 #
b1111011 "
#620
1%
1&
0'
b1111100 !
b1111100 #
b1111100 "
#625
0%
b1111101 !
b1111101 #
b1111101 "
#630
1%
0&
b1111110 !
b1111110 #
b1111110 "
#635
0%
b1111111 !
b1111111 #
b1111111 "
#640
1%
1&
1'
1(
1)
1*
1+
0,
b111 2
b10000000 !
b10000000 #
b10000000 "
#645
0%
b10000001 !
b10000001 #
b10000001 "
#650
1%
0&
1/
b10000010 !
b10000010 #
b10000010 "
#655
0%
b10000011 !
b10000011 #
b10000011 "
#660
1%
1&
0'
1-
0/
b10000100 !
b10000100 #
b10000100 "
#665
0%
b10000101 !
b10000101 #
b10000101 "
#670
1%
0&
b10000110 !
b10000110 #
b10000110 "
#675
0%
b10000111 !
b10000111 #
b10000111 "
#680
1%
1&
1'
0(
0-
1.
10
b10001000 !
b10001000 #
b10001000 "
#685
0%
b10001001 !
b10001001 #
b10001001 "
#690
1%
0&
1/
b10001010 !
b10001010 #
b10001010 "
#695
0%
b10001011 !
b10001011 #
b10001011 "
#700
1%
1&
0'
1-
0/
b10001100 !
b10001100 #
b10001100 "
#705
0%
b10001101 !
b10001101 #
b10001101 "
#710
1%
0&
b10001110 !
b10001110 #
b10001110 "
#715
0%
b10001111 !
b10001111 #
b10001111 "
#720
1%
1&
1'
1(
0)
0-
0.
00
b10010000 !
b10010000 #
b10010000 "
#725
0%
b10010001 !
b10010001 #
b10010001 "
#730
1%
0&
b10010010 !
b10010010 #
b10010010 "
#735
0%
b10010011 !
b10010011 #
b10010011 "
#740
1%
1&
0'
b10010100 !
b10010100 #
b10010100 "
#745
0%
b10010101 !
b10010101 #
b10010101 "
#750
1%
0&
b10010110 !
b10010110 #
b10010110 "
#755
0%
b10010111 !
b10010111 #
b10010111 "
#760
1%
1&
1'
0(
b10011000 !
b10011000 #
b10011000 "
#765
0%
b10011001 !
b10011001 #
b10011001 "
#770
1%
0&
b10011010 !
b10011010 #
b10011010 "
#775
0%
b10011011 !
b10011011 #
b10011011 "
#780
1%
1&
0'
b10011100 !
b10011100 #
b10011100 "
#785
0%
b10011101 !
b10011101 #
b10011101 "
#790
1%
0&
b10011110 !
b10011110 #
b10011110 "
#795
0%
b10011111 !
b10011111 #
b10011111 "
#800
1%
1&
1'
1(
1)
0*
11
b10100000 !
b10100000 #
b10100000 "
#805
0%
b10100001 !
b10100001 #
b10100001 "
#810
1%
0&
1/
b10100010 !
b10100010 #
b10100010 "
#815
0%
b10100011 !
b10100011 #
b10100011 "
#820
1%
1&
0'
0/
b10100100 !
b10100100 #
b10100100 "
#825
0%
b10100101 !
b10100101 #
b10100101 "
#830
1%
0&
b10100110 !
b10100110 #
b10100110 "
#835
0%
b10100111 !
b10100111 #
b10100111 "
#840
1%
1&
1'
0(
10
b10101000 !
b10101000 #
b10101000 "
#845
0%
b10101001 !
b10101001 #
b10101001 "
#850
1%
0&
1/
b10101010 !
b10101010 #
b10101010 "
#855
0%
b10101011 !
b10101011 #
b10101011 "
#860
1%
1&
0'
0/
b10101100 !
b10101100 #
b10101100 "
#865
0%
b10101101 !
b10101101 #
b10101101 "
#870
1%
0&
b10101110 !
b10101110 #
b10101110 "
#875
0%
b10101111 !
b10101111 #
b10101111 "
#880
1%
1&
1'
1(
0)
00
b10110000 !
b10110000 #
b10110000 "
#885
0%
b10110001 !
b10110001 #
b10110001 "
#890
1%
0&
b10110010 !
b10110010 #
b10110010 "
#895
0%
b10110011 !
b10110011 #
b10110011 "
#900
1%
1&
0'
b10110100 !
b10110100 #
b10110100 "
#905
0%
b10110101 !
b10110101 #
b10110101 "
#910
1%
0&
b10110110 !
b10110110 #
b10110110 "
#915
0%
b10110111 !
b10110111 #
b10110111 "
#920
1%
1&
1'
0(
b10111000 !
b10111000 #
b10111000 "
#925
0%
b10111001 !
b10111001 #
b10111001 "
#930
1%
0&
b10111010 !
b10111010 #
b10111010 "
#935
0%
b10111011 !
b10111011 #
b10111011 "
#940
1%
1&
0'
b10111100 !
b10111100 #
b10111100 "
#945
0%
b10111101 !
b10111101 #
b10111101 "
#950
1%
0&
b10111110 !
b10111110 #
b10111110 "
#955
0%
b10111111 !
b10111111 #
b10111111 "
#960
1%
1&
1'
1(
1)
1*
0+
01
b11000000 !
b11000000 #
b11000000 "
#965
0%
b11000001 !
b11000001 #
b11000001 "
#970
1%
0&
b11000010 !
b11000010 #
b11000010 "
#975
0%
b11000011 !
b11000011 #
b11000011 "
#980
1%
1&
0'
1-
b11000100 !
b11000100 #
b11000100 "
#985
0%
b11000101 !
b11000101 #
b11000101 "
#990
1%
0&
b11000110 !
b11000110 #
b11000110 "
#995
0%
b11000111 !
b11000111 #
b11000111 "
#1000
1%
1&
1'
0(
0-
1.
b11001000 !
b11001000 #
b11001000 "
#1005
0%
b11001001 !
b11001001 #
b11001001 "
#1010
1%
0&
b11001010 !
b11001010 #
b11001010 "
#1015
0%
b11001011 !
b11001011 #
b11001011 "
#1020
1%
1&
0'
1-
b11001100 !
b11001100 #
b11001100 "
#1025
0%
b11001101 !
b11001101 #
b11001101 "
#1030
1%
0&
b11001110 !
b11001110 #
b11001110 "
#1035
0%
b11001111 !
b11001111 #
b11001111 "
#1040
1%
1&
1'
1(
0)
0-
0.
b11010000 !
b11010000 #
b11010000 "
#1045
0%
b11010001 !
b11010001 #
b11010001 "
#1050
1%
0&
b11010010 !
b11010010 #
b11010010 "
#1055
0%
b11010011 !
b11010011 #
b11010011 "
#1060
1%
1&
0'
b11010100 !
b11010100 #
b11010100 "
#1065
0%
b11010101 !
b11010101 #
b11010101 "
#1070
1%
0&
b11010110 !
b11010110 #
b11010110 "
#1075
0%
b11010111 !
b11010111 #
b11010111 "
#1080
1%
1&
1'
0(
b11011000 !
b11011000 #
b11011000 "
#1085
0%
b11011001 !
b11011001 #
b11011001 "
#1090
1%
0&
b11011010 !
b11011010 #
b11011010 "
#1095
0%
b11011011 !
b11011011 #
b11011011 "
#1100
1%
1&
0'
b11011100 !
b11011100 #
b11011100 "
#1105
0%
b11011101 !
b11011101 #
b11011101 "
#1110
1%
0&
b11011110 !
b11011110 #
b11011110 "
#1115
0%
b11011111 !
b11011111 #
b11011111 "
#1120
1%
1&
1'
1(
1)
0*
b11100000 !
b11100000 #
b11100000 "
#1125
0%
b11100001 !
b11100001 #
b11100001 "
#1130
1%
0&
b11100010 !
b11100010 #
b11100010 "
#1135
0%
b11100011 !
b11100011 #
b11100011 "
#1140
1%
1&
0'
b11100100 !
b11100100 #
b11100100 "
#1145
0%
b11100101 !
b11100101 #
b11100101 "
#1150
1%
0&
b11100110 !
b11100110 #
b11100110 "
#1155
0%
b11100111 !
b11100111 #
b11100111 "
#1160
1%
1&
1'
0(
b11101000 !
b11101000 #
b11101000 "
#1165
0%
b11101001 !
b11101001 #
b11101001 "
#1170
1%
0&
b11101010 !
b11101010 #
b11101010 "
#1175
0%
b11101011 !
b11101011 #
b11101011 "
#1180
1%
1&
0'
b11101100 !
b11101100 #
b11101100 "
#1185
0%
b11101101 !
b11101101 #
b11101101 "
#1190
1%
0&
b11101110 !
b11101110 #
b11101110 "
#1195
0%
b11101111 !
b11101111 #
b11101111 "
#1200
1%
1&
1'
1(
0)
b11110000 !
b11110000 #
b11110000 "
#1205
0%
b11110001 !
b11110001 #
b11110001 "
#1210
1%
0&
b11110010 !
b11110010 #
b11110010 "
#1215
0%
b11110011 !
b11110011 #
b11110011 "
#1220
1%
1&
0'
b11110100 !
b11110100 #
b11110100 "
#1225
0%
b11110101 !
b11110101 #
b11110101 "
#1230
1%
0&
b11110110 !
b11110110 #
b11110110 "
#1235
0%
b11110111 !
b11110111 #
b11110111 "
#1240
1%
1&
1'
0(
b11111000 !
b11111000 #
b11111000 "
#1245
0%
b11111001 !
b11111001 #
b11111001 "
#1250
1%
0&
b11111010 !
b11111010 #
b11111010 "
#1255
0%
b11111011 !
b11111011 #
b11111011 "
#1260
1%
1&
0'
b11111100 !
b11111100 #
b11111100 "
#1265
0%
b11111101 !
b11111101 #
b11111101 "
#1270
1%
0&
b11111110 !
b11111110 #
b11111110 "
#1275
0%
b11111111 !
b11111111 #
b11111111 "
#1280
1$
1%
1&
1'
1(
1)
1*
1+
1,
b0 2
b0 !
b0 #
b100000000 "
#1285
0$
0%
b1 !
b1 #
b100000001 "
#1290
b1 2
1%
0&
1/
b10 !
b10 #
b100000010 "
#1295
0%
b11 !
b11 #
b100000011 "
#1300
b10 2
1%
1&
0'
1-
0/
b100 !
b100 #
b100000100 "
#1305
0%
b101 !
b101 #
b100000101 "
#1310
1%
0&
b110 !
b110 #
b100000110 "
#1315
0%
b111 !
b111 #
b100000111 "
#1320
b11 2
1%
1&
1'
0(
0-
1.
10
b1000 !
b1000 #
b100001000 "
#1325
0%
b1001 !
b1001 #
b100001001 "
#1330
1%
0&
1/
b1010 !
b1010 #
b100001010 "
#1335
0%
b1011 !
b1011 #
b100001011 "
#1340
1%
1&
0'
1-
0/
b1100 !
b1100 #
b100001100 "
#1345
0%
b1101 !
b1101 #
b100001101 "
#1350
1%
0&
b1110 !
b1110 #
b100001110 "
#1355
0%
b1111 !
b1111 #
b100001111 "
#1360
1%
1&
1'
1(
0)
b100 2
0-
0.
00
b10000 !
b10000 #
b100010000 "
#1365
0%
b10001 !
b10001 #
b100010001 "
#1370
1%
0&
b10010 !
b10010 #
b100010010 "
#1375
0%
b10011 !
b10011 #
b100010011 "
#1380
1%
1&
0'
b10100 !
b10100 #
b100010100 "
#1385
0%
b10101 !
b10101 #
b100010101 "
#1390
1%
0&
b10110 !
b10110 #
b100010110 "
#1395
0%
b10111 !
b10111 #
b100010111 "
#1400
1%
1&
1'
0(
b11000 !
b11000 #
b100011000 "
#1405
0%
b11001 !
b11001 #
b100011001 "
#1410
1%
0&
b11010 !
b11010 #
b100011010 "
#1415
0%
b11011 !
b11011 #
b100011011 "
#1420
1%
1&
0'
b11100 !
b11100 #
b100011100 "
#1425
0%
b11101 !
b11101 #
b100011101 "
#1430
1%
0&
b11110 !
b11110 #
b100011110 "
#1435
0%
b11111 !
b11111 #
b100011111 "
#1440
b101 2
1%
1&
1'
1(
1)
0*
11
b100000 !
b100000 #
b100100000 "
#1445
0%
b100001 !
b100001 #
b100100001 "
#1450
1%
0&
1/
b100010 !
b100010 #
b100100010 "
#1455
0%
b100011 !
b100011 #
b100100011 "
#1460
1%
1&
0'
0/
b100100 !
b100100 #
b100100100 "
#1465
0%
b100101 !
b100101 #
b100100101 "
#1470
1%
0&
b100110 !
b100110 #
b100100110 "
#1475
0%
b100111 !
b100111 #
b100100111 "
#1480
1%
1&
1'
0(
10
b101000 !
b101000 #
b100101000 "
#1485
0%
b101001 !
b101001 #
b100101001 "
#1490
1%
0&
1/
b101010 !
b101010 #
b100101010 "
#1495
0%
b101011 !
b101011 #
b100101011 "
#1500
1%
1&
0'
0/
b101100 !
b101100 #
b100101100 "
#1505
0%
b101101 !
b101101 #
b100101101 "
#1510
1%
0&
b101110 !
b101110 #
b100101110 "
#1515
0%
b101111 !
b101111 #
b100101111 "
#1520
1%
1&
1'
1(
0)
00
b110000 !
b110000 #
b100110000 "
#1525
0%
b110001 !
b110001 #
b100110001 "
#1530
1%
0&
b110010 !
b110010 #
b100110010 "
#1535
0%
b110011 !
b110011 #
b100110011 "
#1540
1%
1&
0'
b110100 !
b110100 #
b100110100 "
#1545
0%
b110101 !
b110101 #
b100110101 "
#1550
1%
0&
b110110 !
b110110 #
b100110110 "
#1555
0%
b110111 !
b110111 #
b100110111 "
#1560
1%
1&
1'
0(
b111000 !
b111000 #
b100111000 "
#1565
0%
b111001 !
b111001 #
b100111001 "
#1570
1%
0&
b111010 !
b111010 #
b100111010 "
#1575
0%
b111011 !
b111011 #
b100111011 "
#1580
1%
1&
0'
b111100 !
b111100 #
b100111100 "
#1585
0%
b111101 !
b111101 #
b100111101 "
#1590
1%
0&
b111110 !
b111110 #
b100111110 "
#1595
0%
b111111 !
b111111 #
b100111111 "
#1600
1%
1&
1'
1(
1)
1*
0+
b110 2
01
b1000000 !
b1000000 #
b101000000 "
#1605
0%
b1000001 !
b1000001 #
b101000001 "
#1610
1%
0&
b1000010 !
b1000010 #
b101000010 "
#1615
0%
b1000011 !
b1000011 #
b101000011 "
#1620
1%
1&
0'
1-
b1000100 !
b1000100 #
b101000100 "
#1625
0%
b1000101 !
b1000101 #
b101000101 "
#1630
1%
0&
b1000110 !
b1000110 #
b101000110 "
#1635
0%
b1000111 !
b1000111 #
b101000111 "
#1640
1%
1&
1'
0(
0-
1.
b1001000 !
b1001000 #
b101001000 "
#1645
0%
b1001001 !
b1001001 #
b101001001 "
#1650
1%
0&
b1001010 !
b1001010 #
b101001010 "
#1655
0%
b1001011 !
b1001011 #
b101001011 "
#1660
1%
1&
0'
1-
b1001100 !
b1001100 #
b101001100 "
#1665
0%
b1001101 !
b1001101 #
b101001101 "
#1670
1%
0&
b1001110 !
b1001110 #
b101001110 "
#1675
0%
b1001111 !
b1001111 #
b101001111 "
#1680
1%
1&
1'
1(
0)
0-
0.
b1010000 !
b1010000 #
b101010000 "
#1685
0%
b1010001 !
b1010001 #
b101010001 "
#1690
1%
0&
b1010010 !
b1010010 #
b101010010 "
#1695
0%
b1010011 !
b1010011 #
b101010011 "
#1700
1%
1&
0'
b1010100 !
b1010100 #
b101010100 "
#1705
0%
b1010101 !
b1010101 #
b101010101 "
#1710
1%
0&
b1010110 !
b1010110 #
b101010110 "
#1715
0%
b1010111 !
b1010111 #
b101010111 "
#1720
1%
1&
1'
0(
b1011000 !
b1011000 #
b101011000 "
#1725
0%
b1011001 !
b1011001 #
b101011001 "
#1730
1%
0&
b1011010 !
b1011010 #
b101011010 "
#1735
0%
b1011011 !
b1011011 #
b101011011 "
#1740
1%
1&
0'
b1011100 !
b1011100 #
b101011100 "
#1745
0%
b1011101 !
b1011101 #
b101011101 "
#1750
1%
0&
b1011110 !
b1011110 #
b101011110 "
#1755
0%
b1011111 !
b1011111 #
b101011111 "
#1760
1%
1&
1'
1(
1)
0*
b1100000 !
b1100000 #
b101100000 "
#1765
0%
b1100001 !
b1100001 #
b101100001 "
#1770
1%
0&
b1100010 !
b1100010 #
b101100010 "
#1775
0%
b1100011 !
b1100011 #
b101100011 "
#1780
1%
1&
0'
b1100100 !
b1100100 #
b101100100 "
#1785
0%
b1100101 !
b1100101 #
b101100101 "
#1790
1%
0&
b1100110 !
b1100110 #
b101100110 "
#1795
0%
b1100111 !
b1100111 #
b101100111 "
#1800
1%
1&
1'
0(
b1101000 !
b1101000 #
b101101000 "
#1805
0%
b1101001 !
b1101001 #
b101101001 "
#1810
1%
0&
b1101010 !
b1101010 #
b101101010 "
#1815
0%
b1101011 !
b1101011 #
b101101011 "
#1820
1%
1&
0'
b1101100 !
b1101100 #
b101101100 "
#1825
0%
b1101101 !
b1101101 #
b101101101 "
#1830
1%
0&
b1101110 !
b1101110 #
b101101110 "
#1835
0%
b1101111 !
b1101111 #
b101101111 "
#1840
1%
1&
1'
1(
0)
b1110000 !
b1110000 #
b101110000 "
#1845
0%
b1110001 !
b1110001 #
b101110001 "
#1850
1%
0&
b1110010 !
b1110010 #
b101110010 "
#1855
0%
b1110011 !
b1110011 #
b101110011 "
#1860
1%
1&
0'
b1110100 !
b1110100 #
b101110100 "
#1865
0%
b1110101 !
b1110101 #
b101110101 "
#1870
1%
0&
b1110110 !
b1110110 #
b101110110 "
#1875
0%
b1110111 !
b1110111 #
b101110111 "
#1880
1%
1&
1'
0(
b1111000 !
b1111000 #
b101111000 "
#1885
0%
b1111001 !
b1111001 #
b101111001 "
#1890
1%
0&
b1111010 !
b1111010 #
b101111010 "
#1895
0%
b1111011 !
b1111011 #
b101111011 "
#1900
1%
1&
0'
b1111100 !
b1111100 #
b101111100 "
#1905
0%
b1111101 !
b1111101 #
b101111101 "
#1910
1%
0&
b1111110 !
b1111110 #
b101111110 "
#1915
0%
b1111111 !
b1111111 #
b101111111 "
#1920
1%
1&
1'
1(
1)
1*
1+
0,
b111 2
b10000000 !
b10000000 #
b110000000 "
#1925
0%
b10000001 !
b10000001 #
b110000001 "
#1930
1%
0&
1/
b10000010 !
b10000010 #
b110000010 "
#1935
0%
b10000011 !
b10000011 #
b110000011 "
#1940
1%
1&
0'
1-
0/
b10000100 !
b10000100 #
b110000100 "
#1945
0%
b10000101 !
b10000101 #
b110000101 "
#1950
1%
0&
b10000110 !
b10000110 #
b110000110 "
#1955
0%
b10000111 !
b10000111 #
b110000111 "
#1960
1%
1&
1'
0(
0-
1.
10
b10001000 !
b10001000 #
b110001000 "
#1965
0%
b10001001 !
b10001001 #
b110001001 "
#1970
1%
0&
1/
b10001010 !
b10001010 #
b110001010 "
#1975
0%
b10001011 !
b10001011 #
b110001011 "
#1980
1%
1&
0'
1-
0/
b10001100 !
b10001100 #
b110001100 "
#1985
0%
b10001101 !
b10001101 #
b110001101 "
#1990
1%
0&
b10001110 !
b10001110 #
b110001110 "
#1995
0%
b10001111 !
b10001111 #
b110001111 "
#2000
1%
1&
1'
1(
0)
0-
0.
00
b10010000 !
b10010000 #
b110010000 "
#2005
0%
b10010001 !
b10010001 #
b110010001 "
#2010
1%
0&
b10010010 !
b10010010 #
b110010010 "
#2015
0%
b10010011 !
b10010011 #
b110010011 "
#2020
1%
1&
0'
b10010100 !
b10010100 #
b110010100 "
#2025
0%
b10010101 !
b10010101 #
b110010101 "
#2030
1%
0&
b10010110 !
b10010110 #
b110010110 "
#2035
0%
b10010111 !
b10010111 #
b110010111 "
#2040
1%
1&
1'
0(
b10011000 !
b10011000 #
b110011000 "
#2045
0%
b10011001 !
b10011001 #
b110011001 "
#2050
1%
0&
b10011010 !
b10011010 #
b110011010 "
#2055
0%
b10011011 !
b10011011 #
b110011011 "
#2060
1%
1&
0'
b10011100 !
b10011100 #
b110011100 "
#2065
0%
b10011101 !
b10011101 #
b110011101 "
#2070
1%
0&
b10011110 !
b10011110 #
b110011110 "
#2075
0%
b10011111 !
b10011111 #
b110011111 "
#2080
1%
1&
1'
1(
1)
0*
11
b10100000 !
b10100000 #
b110100000 "
#2085
0%
b10100001 !
b10100001 #
b110100001 "
#2090
1%
0&
1/
b10100010 !
b10100010 #
b110100010 "
#2095
0%
b10100011 !
b10100011 #
b110100011 "
#2100
1%
1&
0'
0/
b10100100 !
b10100100 #
b110100100 "
#2105
0%
b10100101 !
b10100101 #
b110100101 "
#2110
1%
0&
b10100110 !
b10100110 #
b110100110 "
#2115
0%
b10100111 !
b10100111 #
b110100111 "
#2120
1%
1&
1'
0(
10
b10101000 !
b10101000 #
b110101000 "
#2125
0%
b10101001 !
b10101001 #
b110101001 "
#2130
1%
0&
1/
b10101010 !
b10101010 #
b110101010 "
#2135
0%
b10101011 !
b10101011 #
b110101011 "
#2140
1%
1&
0'
0/
b10101100 !
b10101100 #
b110101100 "
#2145
0%
b10101101 !
b10101101 #
b110101101 "
#2150
1%
0&
b10101110 !
b10101110 #
b110101110 "
#2155
0%
b10101111 !
b10101111 #
b110101111 "
#2160
1%
1&
1'
1(
0)
00
b10110000 !
b10110000 #
b110110000 "
#2165
0%
b10110001 !
b10110001 #
b110110001 "
#2170
1%
0&
b10110010 !
b10110010 #
b110110010 "
#2175
0%
b10110011 !
b10110011 #
b110110011 "
#2180
1%
1&
0'
b10110100 !
b10110100 #
b110110100 "
#2185
0%
b10110101 !
b10110101 #
b110110101 "
#2190
1%
0&
b10110110 !
b10110110 #
b110110110 "
#2195
0%
b10110111 !
b10110111 #
b110110111 "
#2200
1%
1&
1'
0(
b10111000 !
b10111000 #
b110111000 "
#2205
0%
b10111001 !
b10111001 #
b110111001 "
#2210
1%
0&
b10111010 !
b10111010 #
b110111010 "
#2215
0%
b10111011 !
b10111011 #
b110111011 "
#2220
1%
1&
0'
b10111100 !
b10111100 #
b110111100 "
#2225
0%
b10111101 !
b10111101 #
b110111101 "
#2230
1%
0&
b10111110 !
b10111110 #
b110111110 "
#2235
0%
b10111111 !
b10111111 #
b110111111 "
#2240
1%
1&
1'
1(
1)
1*
0+
01
b11000000 !
b11000000 #
b111000000 "
#2245
0%
b11000001 !
b11000001 #
b111000001 "
#2250
1%
0&
b11000010 !
b11000010 #
b111000010 "
#2255
0%
b11000011 !
b11000011 #
b111000011 "
#2260
1%
1&
0'
1-
b11000100 !
b11000100 #
b111000100 "
#2265
0%
b11000101 !
b11000101 #
b111000101 "
#2270
1%
0&
b11000110 !
b11000110 #
b111000110 "
#2275
0%
b11000111 !
b11000111 #
b111000111 "
