CPU/CLA_4.v
`ifndef CLA_4_V
`define CLA_4_V

module CLA_4(
    input[3:0] X,
    input[3:0] Y,
    input[0:0] Cin,
    output[3:0] S,
    output[0:0] Cout
);

    wire[3:0] P=X|Y;
    wire[3:0] G=X&Y;
    wire[3:0] Gn=~G;

    and i1(P0Gn0,P[0],Gn[0]);
    xor(S[0],P0Gn0,Cin);
    nand(P0Cin0,P[0],Cin);
    nand(Cout0,Gn[0],P0Cin0);

    and(P1Gn1,P[1],Gn[1]);
    xor(S[1],P1Gn1,Cout0);
    nand(P1P0Cin0,P[1],P[0],Cin);
    nand(P1G0,P[1],G[0]);
    nand(Cout1,Gn[1],P1G0,P1P0Cin0);

    and(P2Gn2,P[2],Gn[2]);
    xor(S[2],P2Gn2,Cout1);
    nand(P2P1P0Cin0,P[2],P[1],P[0],Cin);
    nand(P2P1G0,P[2],P[1],G[0]);
    nand(P2G1,P[2],G[1]);
    nand(Cout2,Gn[2],P2G1,P2P1G0,P2P1P0Cin0);

    and(P3Gn3,P[3],Gn[3]);
    xor(S[3],P3Gn3,Cout2);
    nand(P3P2P1P0Cin0,P[3],P[2],P[1],P[0],Cin);
    nand(P3P2P1G0,P[3],P[2],P[1],G[0]);
    nand(P3P2G1,P[3],P[2],G[1]);
    nand(P3G2,P[3],G[2]);
    nand(Cout,Gn[3],P3G2,P3P2G1,P3P2P1G0,P3P2P1P0Cin0);

endmodule

`endif

CLA/CLA_16/CLA_16.v
`ifndef CLA_16_V
`define CLA_16_V

`include "CLA/CLA_4/CLA_4.v"
module CLA_16 (
    input [15:0]X,
    input [15:0]Y,
    input Cin,
    output [15:0] S,
    output Cout
);
    wire Cout0, Cout1, Cout2;
    CLA_4 add0 (X[3:0], Y[3:0], Cin, S[3:0], Cout0);
    CLA_4 add1 (X[7:4], Y[7:4], Cout0, S[7:4], Cout1);
    CLA_4 add2 (X[11:8], Y[11:8], Cout1, S[11:8], Cout2);
    CLA_4 add3 (X[15:12], Y[15:12], Cout2, S[15:12], Cout);
endmodule

`endif

CLA/CLA_32/CLA_32.v
`ifndef CLA_32_V
`define CLA_32_V

`include "CLA/CLA_16/CLA_16.v"
module CLA_32 (
    input [31:0]X,Y,
    input Cin,
    output [31:0] S,
    output Cout
);
    wire Cout0;
    CLA_16 add0(X[15:0],Y[15:0],Cin,S[15:0],Cout0);
    CLA_16 add1(X[31:16],Y[31:16],Cout0,S[31:16],Cout);
endmodule

`endif

CLA/CLA_32/CLA_32_tb.v
`timescale 1ns/1ns
`include "CLA_32.v"

module tb_CLA_32();
    reg[31:0] X,Y;
    reg Cin=0;
    integer j;
    initial begin
        for(j=0;j<100;j++)begin
            X=j;
            Y=16'hF-j;
            #100;
        end
    end

    CLA_32 data(
        .X(X),
        .Y(Y),
        .Cin(Cin)
    );
    initial begin
        $dumpfile("CLA_32.vcd");
        $dumpvars(0,tb_CLA_32);
        #10000 $finish;
    end
endmodule

CLA/CLA_32/CLA_32.vcd
$date
	Tue Oct 31 08:37:42 2023
$end
$version
	Icarus Verilog
$end
$timescale
	1ns
$end
$scope module tb_CLA_32 $end
$var reg 1 ! Cin $end
$var reg 32 " X [31:0] $end
$var reg 32 # Y [31:0] $end
$var integer 32 $ j [31:0] $end
$scope module data $end
$var wire 1 ! Cin $end
$var wire 32 % X [31:0] $end
$var wire 32 & Y [31:0] $end
$var wire 32 ' S [31:0] $end
$var wire 1 ( Cout0 $end
$var wire 1 ) Cout $end
$scope module add0 $end
$var wire 1 ! Cin $end
$var wire 16 * X [15:0] $end
$var wire 16 + Y [15:0] $end
$var wire 16 , S [15:0] $end
$var wire 1 - Cout2 $end
$var wire 1 . Cout1 $end
$var wire 1 / Cout0 $end
$var wire 1 ( Cout $end
$scope module add0 $end
$var wire 1 ! Cin $end
$var wire 1 / Cout $end
$var wire 1 0 Cout0 $end
$var wire 1 1 Cout1 $end
$var wire 1 2 Cout2 $end
$var wire 4 3 G [3:0] $end
$var wire 4 4 Gn [3:0] $end
$var wire 4 5 P [3:0] $end
$var wire 1 6 P0Cin0 $end
$var wire 1 7 P0Gn0 $end
$var wire 1 8 P1G0 $end
$var wire 1 9 P1Gn1 $end
$var wire 1 : P1P0Cin0 $end
$var wire 1 ; P2G1 $end
$var wire 1 < P2Gn2 $end
$var wire 1 = P2P1G0 $end
$var wire 1 > P2P1P0Cin0 $end
$var wire 1 ? P3G2 $end
$var wire 1 @ P3Gn3 $end
$var wire 1 A P3P2G1 $end
$var wire 1 B P3P2P1G0 $end
$var wire 1 C P3P2P1P0Cin0 $end
$var wire 4 D X [3:0] $end
$var wire 4 E Y [3:0] $end
$var wire 4 F S [3:0] $end
$upscope $end
$scope module add1 $end
$var wire 1 / Cin $end
$var wire 1 . Cout $end
$var wire 1 G Cout0 $end
$var wire 1 H Cout1 $end
$var wire 1 I Cout2 $end
$var wire 4 J G [3:0] $end
$var wire 4 K Gn [3:0] $end
$var wire 4 L P [3:0] $end
$var wire 1 M P0Cin0 $end
$var wire 1 N P0Gn0 $end
$var wire 1 O P1G0 $end
$var wire 1 P P1Gn1 $end
$var wire 1 Q P1P0Cin0 $end
$var wire 1 R P2G1 $end
$var wire 1 S P2Gn2 $end
$var wire 1 T P2P1G0 $end
$var wire 1 U P2P1P0Cin0 $end
$var wire 1 V P3G2 $end
$var wire 1 W P3Gn3 $end
$var wire 1 X P3P2G1 $end
$var wire 1 Y P3P2P1G0 $end
$var wire 1 Z P3P2P1P0Cin0 $end
$var wire 4 [ X [3:0] $end
$var wire 4 \ Y [3:0] $end
$var wire 4 ] S [3:0] $end
$upscope $end
$scope module add2 $end
$var wire 1 . Cin $end
$var wire 1 - Cout $end
$var wire 1 ^ Cout0 $end
$var wire 1 _ Cout1 $end
$var wire 1 ` Cout2 $end
$var wire 4 a G [3:0] $end
$var wire 4 b Gn [3:0] $end
$var wire 4 c P [3:0] $end
$var wire 1 d P0Cin0 $end
$var wire 1 e P0Gn0 $end
$var wire 1 f P1G0 $end
$var wire 1 g P1Gn1 $end
$var wire 1 h P1P0Cin0 $end
$var wire 1 i P2G1 $end
$var wire 1 j P2Gn2 $end
$var wire 1 k P2P1G0 $end
$var wire 1 l P2P1P0Cin0 $end
$var wire 1 m P3G2 $end
$var wire 1 n P3Gn3 $end
$var wire 1 o P3P2G1 $end
$var wire 1 p P3P2P1G0 $end
$var wire 1 q P3P2P1P0Cin0 $end
$var wire 4 r X [3:0] $end
$var wire 4 s Y [3:0] $end
$var wire 4 t S [3:0] $end
$upscope $end
$scope module add3 $end
$var wire 1 - Cin $end
$var wire 1 ( Cout $end
$var wire 1 u Cout0 $end
$var wire 1 v Cout1 $end
$var wire 1 w Cout2 $end
$var wire 4 x G [3:0] $end
$var wire 4 y Gn [3:0] $end
$var wire 4 z P [3:0] $end
$var wire 1 { P0Cin0 $end
$var wire 1 | P0Gn0 $end
$var wire 1 } P1G0 $end
$var wire 1 ~ P1Gn1 $end
$var wire 1 !" P1P0Cin0 $end
$var wire 1 "" P2G1 $end
$var wire 1 #" P2Gn2 $end
$var wire 1 $" P2P1G0 $end
$var wire 1 %" P2P1P0Cin0 $end
$var wire 1 &" P3G2 $end
$var wire 1 '" P3Gn3 $end
$var wire 1 (" P3P2G1 $end
$var wire 1 )" P3P2P1G0 $end
$var wire 1 *" P3P2P1P0Cin0 $end
$var wire 4 +" X [3:0] $end
$var wire 4 ," Y [3:0] $end
$var wire 4 -" S [3:0] $end
$upscope $end
$upscope $end
$scope module add1 $end
$var wire 1 ( Cin $end
$var wire 16 ." X [15:0] $end
$var wire 16 /" Y [15:0] $end
$var wire 16 0" S [15:0] $end
$var wire 1 1" Cout2 $end
$var wire 1 2" Cout1 $end
$var wire 1 3" Cout0 $end
$var wire 1 ) Cout $end
$scope module add0 $end
$var wire 1 ( Cin $end
$var wire 1 3" Cout $end
$var wire 1 4" Cout0 $end
$var wire 1 5" Cout1 $end
$var wire 1 6" Cout2 $end
$var wire 4 7" G [3:0] $end
$var wire 4 8" Gn [3:0] $end
$var wire 4 9" P [3:0] $end
$var wire 1 :" P0Cin0 $end
$var wire 1 ;" P0Gn0 $end
$var wire 1 <" P1G0 $end
$var wire 1 =" P1Gn1 $end
$var wire 1 >" P1P0Cin0 $end
$var wire 1 ?" P2G1 $end
$var wire 1 @" P2Gn2 $end
$var wire 1 A" P2P1G0 $end
$var wire 1 B" P2P1P0Cin0 $end
$var wire 1 C" P3G2 $end
$var wire 1 D" P3Gn3 $end
$var wire 1 E" P3P2G1 $end
$var wire 1 F" P3P2P1G0 $end
$var wire 1 G" P3P2P1P0Cin0 $end
$var wire 4 H" X [3:0] $end
$var wire 4 I" Y [3:0] $end
$var wire 4 J" S [3:0] $end
$upscope $end
$scope module add1 $end
$var wire 1 3" Cin $end
$var wire 1 2" Cout $end
$var wire 1 K" Cout0 $end
$var wire 1 L" Cout1 $end
$var wire 1 M" Cout2 $end
$var wire 4 N" G [3:0] $end
$var wire 4 O" Gn [3:0] $end
$var wire 4 P" P [3:0] $end
$var wire 1 Q" P0Cin0 $end
$var wire 1 R" P0Gn0 $end
$var wire 1 S" P1G0 $end
$var wire 1 T" P1Gn1 $end
$var wire 1 U" P1P0Cin0 $end
$var wire 1 V" P2G1 $end
$var wire 1 W" P2Gn2 $end
$var wire 1 X" P2P1G0 $end
$var wire 1 Y" P2P1P0Cin0 $end
$var wire 1 Z" P3G2 $end
$var wire 1 [" P3Gn3 $end
$var wire 1 \" P3P2G1 $end
$var wire 1 ]" P3P2P1G0 $end
$var wire 1 ^" P3P2P1P0Cin0 $end
$var wire 4 _" X [3:0] $end
$var wire 4 `" Y [3:0] $end
$var wire 4 a" S [3:0] $end
$upscope $end
$scope module add2 $end
$var wire 1 2" Cin $end
$var wire 1 1" Cout $end
$var wire 1 b" Cout0 $end
$var wire 1 c" Cout1 $end
$var wire 1 d" Cout2 $end
$var wire 4 e" G [3:0] $end
$var wire 4 f" Gn [3:0] $end
$var wire 4 g" P [3:0] $end
$var wire 1 h" P0Cin0 $end
$var wire 1 i" P0Gn0 $end
$var wire 1 j" P1G0 $end
$var wire 1 k" P1Gn1 $end
$var wire 1 l" P1P0Cin0 $end
$var wire 1 m" P2G1 $end
$var wire 1 n" P2Gn2 $end
$var wire 1 o" P2P1G0 $end
$var wire 1 p" P2P1P0Cin0 $end
$var wire 1 q" P3G2 $end
$var wire 1 r" P3Gn3 $end
$var wire 1 s" P3P2G1 $end
$var wire 1 t" P3P2P1G0 $end
$var wire 1 u" P3P2P1P0Cin0 $end
$var wire 4 v" X [3:0] $end
$var wire 4 w" Y [3:0] $end
$var wire 4 x" S [3:0] $end
$upscope $end
$scope module add3 $end
$var wire 1 1" Cin $end
$var wire 1 ) Cout $end
$var wire 1 y" Cout0 $end
$var wire 1 z" Cout1 $end
$var wire 1 {" Cout2 $end
$var wire 4 |" G [3:0] $end
$var wire 4 }" Gn [3:0] $end
$var wire 4 ~" P [3:0] $end
$var wire 1 !# P0Cin0 $end
$var wire 1 "# P0Gn0 $end
$var wire 1 ## P1G0 $end
$var wire 1 $# P1Gn1 $end
$var wire 1 %# P1P0Cin0 $end
$var wire 1 &# P2G1 $end
$var wire 1 '# P2Gn2 $end
$var wire 1 (# P2P1G0 $end
$var wire 1 )# P2P1P0Cin0 $end
$var wire 1 *# P3G2 $end
$var wire 1 +# P3Gn3 $end
$var wire 1 ,# P3P2G1 $end
$var wire 1 -# P3P2P1G0 $end
$var wire 1 .# P3P2P1P0Cin0 $end
$var wire 4 /# X [3:0] $end
$var wire 4 0# Y [3:0] $end
$var wire 4 1# S [3:0] $end
$upscope $end
$upscope $end
$upscope $end
$upscope $end
$enddefinitions $end
#0
$dumpvars
b0 1#
b0 0#
b0 /#
1.#
1-#
1,#
0+#
1*#
1)#
1(#
0'#
1&#
1%#
0$#
1##
0"#
1!#
b0 ~"
b1111 }"
b0 |"
0{"
0z"
0y"
b0 x"
b0 w"
b0 v"
1u"
1t"
1s"
0r"
1q"
1p"
1o"
0n"
1m"
1l"
0k"
1j"
0i"
1h"
b0 g"
b1111 f"
b0 e"
0d"
0c"
0b"
b0 a"
b0 `"
b0 _"
1^"
1]"
1\"
0["
1Z"
1Y"
1X"
0W"
1V"
1U"
0T"
1S"
0R"
1Q"
b0 P"
b1111 O"
b0 N"
0M"
0L"
0K"
b0 J"
b0 I"
b0 H"
1G"
1F"
1E"
0D"
1C"
1B"
1A"
0@"
1?"
1>"
0="
1<"
0;"
1:"
b0 9"
b1111 8"
b0 7"
06"
05"
04"
03"
02"
01"
b0 0"
b0 /"
b0 ."
b0 -"
b0 ,"
b0 +"
1*"
1)"
1("
0'"
1&"
1%"
1$"
0#"
1""
1!"
0~
1}
0|
1{
b0 z
b1111 y
b0 x
0w
0v
0u
b0 t
b0 s
b0 r
1q
1p
1o
0n
1m
1l
1k
0j
1i
1h
0g
1f
0e
1d
b0 c
b1111 b
b0 a
0`
0_
0^
b0 ]
b0 \
b0 [
1Z
1Y
1X
0W
1V
1U
1T
0S
1R
1Q
0P
1O
0N
1M
b0 L
b1111 K
b0 J
0I
0H
0G
b1111 F
b1111 E
b0 D
1C
1B
1A
1@
1?
1>
1=
1<
1;
1:
19
18
17
16
b1111 5
b1111 4
b0 3
02
01
00
0/
0.
0-
b1111 ,
b1111 +
b0 *
0)
0(
b1111 '
b1111 &
b0 %
b0 $
b1111 #
b0 "
0!
$end
#100
b1110 E
b1 D
b1110 +
b1 *
b1110 #
b1110 &
b1 "
b1 %
b1 $
#200
b1101 E
b10 D
b1101 +
b10 *
b1101 #
b1101 &
b10 "
b10 %
b10 $
#300
b1100 E
b11 D
b1100 +
b11 *
b1100 #
b1100 &
b11 "
b11 %
b11 $
#400
b1011 E
b100 D
b1011 +
b100 *
b1011 #
b1011 &
b100 "
b100 %
b100 $
#500
b1010 E
b101 D
b1010 +
b101 *
b1010 #
b1010 &
b101 "
b101 %
b101 $
#600
b1001 E
b110 D
b1001 +
b110 *
b1001 #
b1001 &
b110 "
b110 %
b110 $
#700
b1000 E
b111 D
b1000 +
b111 *
b1000 #
b1000 &
b111 "
b111 %
b111 $
#800
b111 E
b1000 D
b111 +
b1000 *
b111 #
b111 &
b1000 "
b1000 %
b1000 $
#900
b110 E
b1001 D
b110 +
b1001 *
b110 #
b110 &
b1001 "
b1001 %
b1001 $
#1000
b101 E
b1010 D
b101 +
b1010 *
b101 #
b101 &
b1010 "
b1010 %
b1010 $
#1100
b100 E
b1011 D
b100 +
b1011 *
b100 #
b100 &
b1011 "
b1011 %
b1011 $
#1200
b11 E
b1100 D
b11 +
b1100 *
b11 #
b11 &
b1100 "
b1100 %
b1100 $
#1300
b10 E
b1101 D
b10 +
b1101 *
b10 #
b10 &
b1101 "
b1101 %
b1101 $
#1400
b1 E
b1110 D
b1 +
b1110 *
b1 #
b1 &
b1110 "
b1110 %
b1110 $
#1500
b0 E
b1111 D
b0 +
b1111 *
b0 #
b0 &
b1111 "
b1111 %
b1111 $
#1600
1)
1y"
1z"
1{"
0.#
0!#
0%#
0)#
11"
1b"
1c"
1d"
0u"
0h"
0l"
0p"
12"
1K"
1L"
1M"
0^"
0Q"
0U"
0Y"
13"
14"
15"
16"
0G"
0:"
0>"
0B"
1(
1u
1v
1w
0*"
0{
0!"
0%"
1-
1^
1_
1`
0q
0d
0h
0l
1.
b0 t
b1111 ,
b0 -"
b0 J"
b0 a"
b0 x"
b1111 '
b0 0"
b0 1#
1G
1H
1I
1e
1g
1j
1n
1|
1~
1#"
1'"
1;"
1="
1@"
1D"
1R"
1T"
1W"
1["
1i"
1k"
1n"
1r"
1"#
1$#
1'#
1+#
1P
1S
1W
0O
0T
0Y
b1110 K
b1111 c
b1111 z
b1111 9"
b1111 P"
b1111 g"
b1111 ~"
b1111 L
b1 J
b1111 E
b1111 \
b1111 s
b1111 ,"
b1111 I"
b1111 `"
b1111 w"
b1111 0#
b0 D
b1 [
b1111111111111111 +
b1111111111111111 /"
b10000 *
b11111111111111111111111111111111 #
b11111111111111111111111111111111 &
b10000 "
b10000 %
b10000 $
#1700
b1110 E
b1 D
b1111111111111110 +
b10001 *
b11111111111111111111111111111110 #
b11111111111111111111111111111110 &
b10001 "
b10001 %
b10001 $
#1800
b1101 E
b10 D
b1111111111111101 +
b10010 *
b11111111111111111111111111111101 #
b11111111111111111111111111111101 &
b10010 "
b10010 %
b10010 $
#1900
b1100 E
b11 D
b1111111111111100 +
b10011 *
b11111111111111111111111111111100 #
b11111111111111111111111111111100 &
b10011 "
b10011 %
b10011 $
#2000
b1011 E
b100 D
b1111111111111011 +
b10100 *
b11111111111111111111111111111011 #
b11111111111111111111111111111011 &
b10100 "
b10100 %
b10100 $
#2100
b1010 E
b101 D
b1111111111111010 +
b10101 *
b11111111111111111111111111111010 #
b11111111111111111111111111111010 &
b10101 "
b10101 %
b10101 $
#2200
b1001 E
b110 D
b1111111111111001 +
b10110 *
b11111111111111111111111111111001 #
b11111111111111111111111111111001 &
b10110 "
b10110 %
b10110 $
#2300
b1000 E
b111 D
b1111111111111000 +
b10111 *
b11111111111111111111111111111000 #
b11111111111111111111111111111000 &
b10111 "
b10111 %
b10111 $
#2400
b111 E
b1000 D
b1111111111110111 +
b11000 *
b11111111111111111111111111110111 #
b11111111111111111111111111110111 &
b11000 "
b11000 %
b11000 $
#2500
b110 E
b1001 D
b1111111111110110 +
b11001 *
b11111111111111111111111111110110 #
b11111111111111111111111111110110 &
b11001 "
b11001 %
b11001 $
#2600
b101 E
b1010 D
b1111111111110101 +
b11010 *
b11111111111111111111111111110101 #
b11111111111111111111111111110101 &
b11010 "
b11010 %
b11010 $
#2700
b100 E
b1011 D
b1111111111110100 +
b11011 *
b11111111111111111111111111110100 #
b11111111111111111111111111110100 &
b11011 "
b11011 %
b11011 $
#2800
b11 E
b1100 D
b1111111111110011 +
b11100 *
b11111111111111111111111111110011 #
b11111111111111111111111111110011 &
b11100 "
b11100 %
b11100 $
#2900
b10 E
b1101 D
b1111111111110010 +
b11101 *
b11111111111111111111111111110010 #
b11111111111111111111111111110010 &
b11101 "
b11101 %
b11101 $
#3000
b1 E
b1110 D
b1111111111110001 +
b11110 *
b11111111111111111111111111110001 #
b11111111111111111111111111110001 &
b11110 "
b11110 %
b11110 $
#3100
b0 E
b1111 D
b1111111111110000 +
b11111 *
b11111111111111111111111111110000 #
b11111111111111111111111111110000 &
b11111 "
b11111 %
b11111 $
#3200
0G
0P
1O
1T
0R
1Y
0X
b1101 K
b1110 L
b10 J
b1111 E
b1110 \
b0 D
b10 [
b1111111111101111 +
b100000 *
b11111111111111111111111111101111 #
b11111111111111111111111111101111 &
b100000 "
b100000 %
b100000 $
#3300
b1110 E
b1 D
b1111111111101110 +
b100001 *
b11111111111111111111111111101110 #
b11111111111111111111111111101110 &
b100001 "
b100001 %
b100001 $
#3400
b1101 E
b10 D
b1111111111101101 +
b100010 *
b11111111111111111111111111101101 #
b11111111111111111111111111101101 &
b100010 "
b100010 %
b100010 $
#3500
b1100 E
b11 D
b1111111111101100 +
b100011 *
b11111111111111111111111111101100 #
b11111111111111111111111111101100 &
b100011 "
b100011 %
b100011 $
#3600
b1011 E
b100 D
b1111111111101011 +
b100100 *
b11111111111111111111111111101011 #
b11111111111111111111111111101011 &
b100100 "
b100100 %
b100100 $
#3700
b1010 E
b101 D
b1111111111101010 +
b100101 *
b11111111111111111111111111101010 #
b11111111111111111111111111101010 &
b100101 "
b100101 %
b100101 $
#3800
b1001 E
b110 D
b1111111111101001 +
b100110 *
b11111111111111111111111111101001 #
b11111111111111111111111111101001 &
b100110 "
b100110 %
b100110 $
#3900
b1000 E
b111 D
b1111111111101000 +
b100111 *
b11111111111111111111111111101000 #
b11111111111111111111111111101000 &
b100111 "
b100111 %
b100111 $
#4000
b111 E
b1000 D
b1111111111100111 +
b101000 *
b11111111111111111111111111100111 #
b11111111111111111111111111100111 &
b101000 "
b101000 %
b101000 $
#4100
b110 E
b1001 D
b1111111111100110 +
b101001 *
b11111111111111111111111111100110 #
b11111111111111111111111111100110 &
b101001 "
b101001 %
b101001 $
#4200
b101 E
b1010 D
b1111111111100101 +
b101010 *
b11111111111111111111111111100101 #
b11111111111111111111111111100101 &
b101010 "
b101010 %
b101010 $
#4300
b100 E
b1011 D
b1111111111100100 +
b101011 *
b11111111111111111111111111100100 #
b11111111111111111111111111100100 &
b101011 "
b101011 %
b101011 $
#4400
b11 E
b1100 D
b1111111111100011 +
b101100 *
b11111111111111111111111111100011 #
b11111111111111111111111111100011 &
b101100 "
b101100 %
b101100 $
#4500
b10 E
b1101 D
b1111111111100010 +
b101101 *
b11111111111111111111111111100010 #
b11111111111111111111111111100010 &
b101101 "
b101101 %
b101101 $
#4600
b1 E
b1110 D
b1111111111100001 +
b101110 *
b11111111111111111111111111100001 #
b11111111111111111111111111100001 &
b101110 "
b101110 %
b101110 $
#4700
b0 E
b1111 D
b1111111111100000 +
b101111 *
b11111111111111111111111111100000 #
b11111111111111111111111111100000 &
b101111 "
b101111 %
b101111 $
#4800
1G
1P
0O
0T
1R
0Y
1X
b1110 K
b1111 L
b1 J
b1111 E
b1101 \
b0 D
b11 [
b1111111111011111 +
b110000 *
b11111111111111111111111111011111 #
b11111111111111111111111111011111 &
b110000 "
b110000 %
b110000 $
#4900
b1110 E
b1 D
b1111111111011110 +
b110001 *
b11111111111111111111111111011110 #
b11111111111111111111111111011110 &
b110001 "
b110001 %
b110001 $
#5000
b1101 E
b10 D
b1111111111011101 +
b110010 *
b11111111111111111111111111011101 #
b11111111111111111111111111011101 &
b110010 "
b110010 %
b110010 $
#5100
b1100 E
b11 D
b1111111111011100 +
b110011 *
b11111111111111111111111111011100 #
b11111111111111111111111111011100 &
b110011 "
b110011 %
b110011 $
#5200
b1011 E
b100 D
b1111111111011011 +
b110100 *
b11111111111111111111111111011011 #
b11111111111111111111111111011011 &
b110100 "
b110100 %
b110100 $
#5300
b1010 E
b101 D
b1111111111011010 +
b110101 *
b11111111111111111111111111011010 #
b11111111111111111111111111011010 &
b110101 "
b110101 %
b110101 $
#5400
b1001 E
b110 D
b1111111111011001 +
b110110 *
b11111111111111111111111111011001 #
b11111111111111111111111111011001 &
b110110 "
b110110 %
b110110 $
#5500
b1000 E
b111 D
b1111111111011000 +
b110111 *
b11111111111111111111111111011000 #
b11111111111111111111111111011000 &
b110111 "
b110111 %
b110111 $
#5600
b111 E
b1000 D
b1111111111010111 +
b111000 *
b11111111111111111111111111010111 #
b11111111111111111111111111010111 &
b111000 "
b111000 %
b111000 $
#5700
b110 E
b1001 D
b1111111111010110 +
b111001 *
b11111111111111111111111111010110 #
b11111111111111111111111111010110 &
b111001 "
b111001 %
b111001 $
#5800
b101 E
b1010 D
b1111111111010101 +
b111010 *
b11111111111111111111111111010101 #
b11111111111111111111111111010101 &
b111010 "
b111010 %
b111010 $
#5900
b100 E
b1011 D
b1111111111010100 +
b111011 *
b11111111111111111111111111010100 #
b11111111111111111111111111010100 &
b111011 "
b111011 %
b111011 $
#6000
b11 E
b1100 D
b1111111111010011 +
b111100 *
b11111111111111111111111111010011 #
b11111111111111111111111111010011 &
b111100 "
b111100 %
b111100 $
#6100
b10 E
b1101 D
b1111111111010010 +
b111101 *
b11111111111111111111111111010010 #
b11111111111111111111111111010010 &
b111101 "
b111101 %
b111101 $
#6200
b1 E
b1110 D
b1111111111010001 +
b111110 *
b11111111111111111111111111010001 #
b11111111111111111111111111010001 &
b111110 "
b111110 %
b111110 $
#6300
b0 E
b1111 D
b1111111111010000 +
b111111 *
b11111111111111111111111111010000 #
b11111111111111111111111111010000 &
b111111 "
b111111 %
b111111 $
#6400
0G
0S
0H
0P
1O
1T
1Y
0V
b1011 K
b1100 L
b100 J
b1111 E
b1100 \
b0 D
b100 [
b1111111111001111 +
b1000000 *
b11111111111111111111111111001111 #
b11111111111111111111111111001111 &
b1000000 "
b1000000 %
b1000000 $
#6500
b1110 E
b1 D
b1111111111001110 +
b1000001 *
b11111111111111111111111111001110 #
b11111111111111111111111111001110 &
b1000001 "
b1000001 %
b1000001 $
#6600
b1101 E
b10 D
b1111111111001101 +
b1000010 *
b11111111111111111111111111001101 #
b11111111111111111111111111001101 &
b1000010 "
b1000010 %
b1000010 $
#6700
b1100 E
b11 D
b1111111111001100 +
b1000011 *
b11111111111111111111111111001100 #
b11111111111111111111111111001100 &
b1000011 "
b1000011 %
b1000011 $
#6800
b1011 E
b100 D
b1111111111001011 +
b1000100 *
b11111111111111111111111111001011 #
b11111111111111111111111111001011 &
b1000100 "
b1000100 %
b1000100 $
#6900
b1010 E
b101 D
b1111111111001010 +
b1000101 *
b11111111111111111111111111001010 #
b11111111111111111111111111001010 &
b1000101 "
b1000101 %
b1000101 $
#7000
b1001 E
b110 D
b1111111111001001 +
b1000110 *
b11111111111111111111111111001001 #
b11111111111111111111111111001001 &
b1000110 "
b1000110 %
b1000110 $
#7100
b1000 E
b111 D
b1111111111001000 +
b1000111 *
b11111111111111111111111111001000 #
b11111111111111111111111111001000 &
b1000111 "
b1000111 %
b1000111 $
#7200
b111 E
b1000 D
b1111111111000111 +
b1001000 *
b11111111111111111111111111000111 #
b11111111111111111111111111000111 &
b1001000 "
b1001000 %
b1001000 $
#7300
b110 E
b1001 D
b1111111111000110 +
b1001001 *
b11111111111111111111111111000110 #
b11111111111111111111111111000110 &
b1001001 "
b1001001 %
b1001001 $
#7400
b101 E
b1010 D
b1111111111000101 +
b1001010 *
b11111111111111111111111111000101 #
b11111111111111111111111111000101 &
b1001010 "
b1001010 %
b1001010 $
#7500
b100 E
b1011 D
b1111111111000100 +
b1001011 *
b11111111111111111111111111000100 #
b11111111111111111111111111000100 &
b1001011 "
b1001011 %
b1001011 $
#7600
b11 E
b1100 D
b1111111111000011 +
b1001100 *
b11111111111111111111111111000011 #
b11111111111111111111111111000011 &
b1001100 "
b1001100 %
b1001100 $
#7700
b10 E
b1101 D
b1111111111000010 +
b1001101 *
b11111111111111111111111111000010 #
b11111111111111111111111111000010 &
b1001101 "
b1001101 %
b1001101 $
#7800
b1 E
b1110 D
b1111111111000001 +
b1001110 *
b11111111111111111111111111000001 #
b11111111111111111111111111000001 &
b1001110 "
b1001110 %
b1001110 $
#7900
b0 E
b1111 D
b1111111111000000 +
b1001111 *
b11111111111111111111111111000000 #
b11111111111111111111111111000000 &
b1001111 "
b1001111 %
b1001111 $
#8000
1G
1S
1H
1P
0O
0T
0Y
1V
b1110 K
b1111 L
b1 J
b1111 E
b1011 \
b0 D
b101 [
b1111111110111111 +
b1010000 *
b11111111111111111111111110111111 #
b11111111111111111111111110111111 &
b1010000 "
b1010000 %
b1010000 $
#8100
b1110 E
b1 D
b1111111110111110 +
b1010001 *
b11111111111111111111111110111110 #
b11111111111111111111111110111110 &
b1010001 "
b1010001 %
b1010001 $
#8200
b1101 E
b10 D
b1111111110111101 +
b1010010 *
b11111111111111111111111110111101 #
b11111111111111111111111110111101 &
b1010010 "
b1010010 %
b1010010 $
#8300
b1100 E
b11 D
b1111111110111100 +
b1010011 *
b11111111111111111111111110111100 #
b11111111111111111111111110111100 &
b1010011 "
b1010011 %
b1010011 $
#8400
b1011 E
b100 D
b1111111110111011 +
b1010100 *
b11111111111111111111111110111011 #
b11111111111111111111111110111011 &
b1010100 "
b1010100 %
b1010100 $
#8500
b1010 E
b101 D
b1111111110111010 +
b1010101 *
b11111111111111111111111110111010 #
b11111111111111111111111110111010 &
b1010101 "
b1010101 %
b1010101 $
#8600
b1001 E
b110 D
b1111111110111001 +
b1010110 *
b11111111111111111111111110111001 #
b11111111111111111111111110111001 &
b1010110 "
b1010110 %
b1010110 $
#8700
b1000 E
b111 D
b1111111110111000 +
b1010111 *
b11111111111111111111111110111000 #
b11111111111111111111111110111000 &
b1010111 "
b1010111 %
b1010111 $
#8800
b111 E
b1000 D
b1111111110110111 +
b1011000 *
b11111111111111111111111110110111 #
b11111111111111111111111110110111 &
b1011000 "
b1011000 %
b1011000 $
#8900
b110 E
b1001 D
b1111111110110110 +
b1011001 *
b11111111111111111111111110110110 #
b11111111111111111111111110110110 &
b1011001 "
b1011001 %
b1011001 $
#9000
b101 E
b1010 D
b1111111110110101 +
b1011010 *
b11111111111111111111111110110101 #
b11111111111111111111111110110101 &
b1011010 "
b1011010 %
b1011010 $
#9100
b100 E
b1011 D
b1111111110110100 +
b1011011 *
b11111111111111111111111110110100 #
b11111111111111111111111110110100 &
b1011011 "
b1011011 %
b1011011 $
#9200
b11 E
b1100 D
b1111111110110011 +
b1011100 *
b11111111111111111111111110110011 #
b11111111111111111111111110110011 &
b1011100 "
b1011100 %
b1011100 $
#9300
b10 E
b1101 D
b1111111110110010 +
b1011101 *
b11111111111111111111111110110010 #
b11111111111111111111111110110010 &
b1011101 "
b1011101 %
b1011101 $
#9400
b1 E
b1110 D
b1111111110110001 +
b1011110 *
b11111111111111111111111110110001 #
b11111111111111111111111110110001 &
b1011110 "
b1011110 %
b1011110 $
#9500
b0 E
b1111 D
b1111111110110000 +
b1011111 *
b11111111111111111111111110110000 #
b11111111111111111111111110110000 &
b1011111 "
b1011111 %
b1011111 $
#9600
0G
0P
1O
1T
0R
1Y
0X
b1101 K
b1110 L
b10 J
b1111 E
b1010 \
b0 D
b110 [
b1111111110101111 +
b1100000 *
b11111111111111111111111110101111 #
b11111111111111111111111110101111 &
b1100000 "
b1100000 %
b1100000 $
#9700
b1110 E
b1 D
b1111111110101110 +
b1100001 *
b11111111111111111111111110101110 #
b11111111111111111111111110101110 &
b1100001 "
b1100001 %
b1100001 $
#9800
b1101 E
b10 D
b1111111110101101 +
b1100010 *
b11111111111111111111111110101101 #
b11111111111111111111111110101101 &
b1100010 "
b1100010 %
b1100010 $
